{
  "0201": {
    "teryt": "0201",
    "w1_12_19": 2663,
    "w1_20_39": 11817,
    "w1_40_59": 14977,
    "w1_60_69": 8940,
    "w1_70plus": 9388,
    "population": 89762,
    "atLeastOneDose": 48405,
    "fullyVaccinated": 47184
  },
  "0202": {
    "teryt": "0202",
    "w1_12_19": 2774,
    "w1_20_39": 10673,
    "w1_40_59": 15401,
    "w1_60_69": 10607,
    "w1_70plus": 12097,
    "population": 99935,
    "atLeastOneDose": 52260,
    "fullyVaccinated": 51130
  },
  "0203": {
    "teryt": "0203",
    "w1_12_19": 3740,
    "w1_20_39": 11433,
    "w1_40_59": 16463,
    "w1_60_69": 9967,
    "w1_70plus": 10514,
    "population": 88447,
    "atLeastOneDose": 53105,
    "fullyVaccinated": 52006
  },
  "0204": {
    "teryt": "0204",
    "w1_12_19": 1169,
    "w1_20_39": 4137,
    "w1_40_59": 5548,
    "w1_60_69": 3643,
    "w1_70plus": 3501,
    "population": 34552,
    "atLeastOneDose": 18242,
    "fullyVaccinated": 17874
  },
  "0205": {
    "teryt": "0205",
    "w1_12_19": 1603,
    "w1_20_39": 5874,
    "w1_40_59": 8281,
    "w1_60_69": 5782,
    "w1_70plus": 5291,
    "population": 49734,
    "atLeastOneDose": 27232,
    "fullyVaccinated": 26596
  },
  "0206": {
    "teryt": "0206",
    "w1_12_19": 2086,
    "w1_20_39": 7425,
    "w1_40_59": 10874,
    "w1_60_69": 7149,
    "w1_70plus": 6701,
    "population": 63333,
    "atLeastOneDose": 34743,
    "fullyVaccinated": 34008
  },
  "0207": {
    "teryt": "0207",
    "w1_12_19": 1525,
    "w1_20_39": 5723,
    "w1_40_59": 7794,
    "w1_60_69": 4894,
    "w1_70plus": 4880,
    "population": 42824,
    "atLeastOneDose": 25174,
    "fullyVaccinated": 24706
  },
  "0208": {
    "teryt": "0208",
    "w1_12_19": 4386,
    "w1_20_39": 17611,
    "w1_40_59": 25116,
    "w1_60_69": 17282,
    "w1_70plus": 19016,
    "population": 156283,
    "atLeastOneDose": 84450,
    "fullyVaccinated": 82797
  },
  "0209": {
    "teryt": "0209",
    "w1_12_19": 1823,
    "w1_20_39": 6785,
    "w1_40_59": 9811,
    "w1_60_69": 6119,
    "w1_70plus": 5267,
    "population": 55110,
    "atLeastOneDose": 30272,
    "fullyVaccinated": 29631
  },
  "0210": {
    "teryt": "0210",
    "w1_12_19": 1703,
    "w1_20_39": 6995,
    "w1_40_59": 9476,
    "w1_60_69": 5862,
    "w1_70plus": 6163,
    "population": 53852,
    "atLeastOneDose": 30590,
    "fullyVaccinated": 29956
  },
  "0211": {
    "teryt": "0211",
    "w1_12_19": 3811,
    "w1_20_39": 12775,
    "w1_40_59": 18845,
    "w1_60_69": 11257,
    "w1_70plus": 13112,
    "population": 105896,
    "atLeastOneDose": 60837,
    "fullyVaccinated": 59337
  },
  "0212": {
    "teryt": "0212",
    "w1_12_19": 1492,
    "w1_20_39": 5803,
    "w1_40_59": 7405,
    "w1_60_69": 5130,
    "w1_70plus": 4832,
    "population": 45599,
    "atLeastOneDose": 25063,
    "fullyVaccinated": 24578
  },
  "0213": {
    "teryt": "0213",
    "w1_12_19": 1505,
    "w1_20_39": 5279,
    "w1_40_59": 6751,
    "w1_60_69": 3827,
    "w1_70plus": 4007,
    "population": 36800,
    "atLeastOneDose": 21778,
    "fullyVaccinated": 21240
  },
  "0214": {
    "teryt": "0214",
    "w1_12_19": 3992,
    "w1_20_39": 15424,
    "w1_40_59": 19847,
    "w1_60_69": 10420,
    "w1_70plus": 11274,
    "population": 107268,
    "atLeastOneDose": 62204,
    "fullyVaccinated": 60848
  },
  "0215": {
    "teryt": "0215",
    "w1_12_19": 2873,
    "w1_20_39": 11826,
    "w1_40_59": 15065,
    "w1_60_69": 7716,
    "w1_70plus": 8277,
    "population": 76733,
    "atLeastOneDose": 46651,
    "fullyVaccinated": 45600
  },
  "0216": {
    "teryt": "0216",
    "w1_12_19": 2111,
    "w1_20_39": 8008,
    "w1_40_59": 11005,
    "w1_60_69": 5846,
    "w1_70plus": 5777,
    "population": 62997,
    "atLeastOneDose": 33289,
    "fullyVaccinated": 32566
  },
  "0217": {
    "teryt": "0217",
    "w1_12_19": 1557,
    "w1_20_39": 5858,
    "w1_40_59": 7749,
    "w1_60_69": 4784,
    "w1_70plus": 4621,
    "population": 43221,
    "atLeastOneDose": 25040,
    "fullyVaccinated": 24486
  },
  "0218": {
    "teryt": "0218",
    "w1_12_19": 2194,
    "w1_20_39": 8222,
    "w1_40_59": 10915,
    "w1_60_69": 5439,
    "w1_70plus": 4901,
    "population": 55508,
    "atLeastOneDose": 32431,
    "fullyVaccinated": 31532
  },
  "0219": {
    "teryt": "0219",
    "w1_12_19": 5334,
    "w1_20_39": 20153,
    "w1_40_59": 27726,
    "w1_60_69": 17216,
    "w1_70plus": 18317,
    "population": 156015,
    "atLeastOneDose": 90300,
    "fullyVaccinated": 88479
  },
  "0220": {
    "teryt": "0220",
    "w1_12_19": 3541,
    "w1_20_39": 12553,
    "w1_40_59": 16506,
    "w1_60_69": 8864,
    "w1_70plus": 8402,
    "population": 85226,
    "atLeastOneDose": 51006,
    "fullyVaccinated": 49862
  },
  "0221": {
    "teryt": "0221",
    "w1_12_19": 1825,
    "w1_20_39": 6376,
    "w1_40_59": 9314,
    "w1_60_69": 6353,
    "w1_70plus": 6266,
    "population": 55107,
    "atLeastOneDose": 30627,
    "fullyVaccinated": 29972
  },
  "0222": {
    "teryt": "0222",
    "w1_12_19": 1340,
    "w1_20_39": 5818,
    "w1_40_59": 7916,
    "w1_60_69": 4941,
    "w1_70plus": 5018,
    "population": 46623,
    "atLeastOneDose": 25393,
    "fullyVaccinated": 24717
  },
  "0223": {
    "teryt": "0223",
    "w1_12_19": 8097,
    "w1_20_39": 29554,
    "w1_40_59": 35827,
    "w1_60_69": 13685,
    "w1_70plus": 12173,
    "population": 156322,
    "atLeastOneDose": 103142,
    "fullyVaccinated": 100543
  },
  "0224": {
    "teryt": "0224",
    "w1_12_19": 1824,
    "w1_20_39": 7636,
    "w1_40_59": 10323,
    "w1_60_69": 6904,
    "w1_70plus": 7234,
    "population": 64080,
    "atLeastOneDose": 34324,
    "fullyVaccinated": 33525
  },
  "0225": {
    "teryt": "0225",
    "w1_12_19": 2544,
    "w1_20_39": 10603,
    "w1_40_59": 15346,
    "w1_60_69": 9542,
    "w1_70plus": 9685,
    "population": 88386,
    "atLeastOneDose": 48302,
    "fullyVaccinated": 47265
  },
  "0226": {
    "teryt": "0226",
    "w1_12_19": 1553,
    "w1_20_39": 5522,
    "w1_40_59": 7419,
    "w1_60_69": 5048,
    "w1_70plus": 4585,
    "population": 43038,
    "atLeastOneDose": 24576,
    "fullyVaccinated": 24003
  },
  "0261": {
    "teryt": "0261",
    "w1_12_19": 2568,
    "w1_20_39": 9987,
    "w1_40_59": 13741,
    "w1_60_69": 9635,
    "w1_70plus": 11740,
    "population": 78335,
    "atLeastOneDose": 48453,
    "fullyVaccinated": 47397
  },
  "0262": {
    "teryt": "0262",
    "w1_12_19": 3431,
    "w1_20_39": 13635,
    "w1_40_59": 17533,
    "w1_60_69": 10700,
    "w1_70plus": 12096,
    "population": 98436,
    "atLeastOneDose": 58417,
    "fullyVaccinated": 57107
  },
  "0264": {
    "teryt": "0264",
    "w1_12_19": 26855,
    "w1_20_39": 156235,
    "w1_40_59": 132030,
    "w1_60_69": 63937,
    "w1_70plus": 86910,
    "population": 641928,
    "atLeastOneDose": 480775,
    "fullyVaccinated": 470231
  },
  "0265": {
    "teryt": "0265",
    "w1_12_19": 3507,
    "w1_20_39": 12748,
    "w1_40_59": 18429,
    "w1_60_69": 14078,
    "w1_70plus": 14947,
    "population": 109971,
    "atLeastOneDose": 64723,
    "fullyVaccinated": 63351
  },
  "0401": {
    "teryt": "0401",
    "w1_12_19": 2280,
    "w1_20_39": 7982,
    "w1_40_59": 10175,
    "w1_60_69": 6079,
    "w1_70plus": 6469,
    "population": 54891,
    "atLeastOneDose": 33575,
    "fullyVaccinated": 32873
  },
  "0402": {
    "teryt": "0402",
    "w1_12_19": 3461,
    "w1_20_39": 12250,
    "w1_40_59": 14584,
    "w1_60_69": 7721,
    "w1_70plus": 7138,
    "population": 79023,
    "atLeastOneDose": 46039,
    "fullyVaccinated": 45212
  },
  "0403": {
    "teryt": "0403",
    "w1_12_19": 6326,
    "w1_20_39": 18736,
    "w1_40_59": 26374,
    "w1_60_69": 11513,
    "w1_70plus": 10285,
    "population": 120432,
    "atLeastOneDose": 75385,
    "fullyVaccinated": 73931
  },
  "0404": {
    "teryt": "0404",
    "w1_12_19": 2343,
    "w1_20_39": 7521,
    "w1_40_59": 9478,
    "w1_60_69": 5402,
    "w1_70plus": 5020,
    "population": 51657,
    "atLeastOneDose": 30555,
    "fullyVaccinated": 29923
  },
  "0405": {
    "teryt": "0405",
    "w1_12_19": 1787,
    "w1_20_39": 6715,
    "w1_40_59": 8135,
    "w1_60_69": 4584,
    "w1_70plus": 4283,
    "population": 44855,
    "atLeastOneDose": 25956,
    "fullyVaccinated": 25448
  },
  "0406": {
    "teryt": "0406",
    "w1_12_19": 1808,
    "w1_20_39": 5756,
    "w1_40_59": 7465,
    "w1_60_69": 3896,
    "w1_70plus": 3305,
    "population": 40305,
    "atLeastOneDose": 22727,
    "fullyVaccinated": 22257
  },
  "0407": {
    "teryt": "0407",
    "w1_12_19": 6648,
    "w1_20_39": 22766,
    "w1_40_59": 31590,
    "w1_60_69": 18379,
    "w1_70plus": 18063,
    "population": 158496,
    "atLeastOneDose": 99322,
    "fullyVaccinated": 97532
  },
  "0408": {
    "teryt": "0408",
    "w1_12_19": 2541,
    "w1_20_39": 9095,
    "w1_40_59": 11483,
    "w1_60_69": 6240,
    "w1_70plus": 5621,
    "population": 65450,
    "atLeastOneDose": 35573,
    "fullyVaccinated": 34482
  },
  "0409": {
    "teryt": "0409",
    "w1_12_19": 1519,
    "w1_20_39": 6370,
    "w1_40_59": 8077,
    "w1_60_69": 4816,
    "w1_70plus": 4720,
    "population": 45482,
    "atLeastOneDose": 25880,
    "fullyVaccinated": 25222
  },
  "0410": {
    "teryt": "0410",
    "w1_12_19": 3816,
    "w1_20_39": 12713,
    "w1_40_59": 16074,
    "w1_60_69": 8886,
    "w1_70plus": 8148,
    "population": 86119,
    "atLeastOneDose": 50811,
    "fullyVaccinated": 49685
  },
  "0411": {
    "teryt": "0411",
    "w1_12_19": 1746,
    "w1_20_39": 6204,
    "w1_40_59": 7860,
    "w1_60_69": 4487,
    "w1_70plus": 4457,
    "population": 40025,
    "atLeastOneDose": 25192,
    "fullyVaccinated": 24754
  },
  "0412": {
    "teryt": "0412",
    "w1_12_19": 1865,
    "w1_20_39": 6255,
    "w1_40_59": 7595,
    "w1_60_69": 4634,
    "w1_70plus": 4331,
    "population": 43390,
    "atLeastOneDose": 25094,
    "fullyVaccinated": 24650
  },
  "0413": {
    "teryt": "0413",
    "w1_12_19": 1750,
    "w1_20_39": 6198,
    "w1_40_59": 7318,
    "w1_60_69": 4260,
    "w1_70plus": 4195,
    "population": 40826,
    "atLeastOneDose": 24149,
    "fullyVaccinated": 23715
  },
  "0414": {
    "teryt": "0414",
    "w1_12_19": 4215,
    "w1_20_39": 13934,
    "w1_40_59": 17793,
    "w1_60_69": 10272,
    "w1_70plus": 9520,
    "population": 98703,
    "atLeastOneDose": 56904,
    "fullyVaccinated": 55722
  },
  "0415": {
    "teryt": "0415",
    "w1_12_19": 5601,
    "w1_20_39": 16747,
    "w1_40_59": 22498,
    "w1_60_69": 10089,
    "w1_70plus": 8340,
    "population": 109565,
    "atLeastOneDose": 64936,
    "fullyVaccinated": 63560
  },
  "0416": {
    "teryt": "0416",
    "w1_12_19": 1886,
    "w1_20_39": 6669,
    "w1_40_59": 8229,
    "w1_60_69": 5034,
    "w1_70plus": 4597,
    "population": 48322,
    "atLeastOneDose": 27031,
    "fullyVaccinated": 26529
  },
  "0417": {
    "teryt": "0417",
    "w1_12_19": 1376,
    "w1_20_39": 4759,
    "w1_40_59": 6198,
    "w1_60_69": 3504,
    "w1_70plus": 3446,
    "population": 34040,
    "atLeastOneDose": 19699,
    "fullyVaccinated": 19299
  },
  "0418": {
    "teryt": "0418",
    "w1_12_19": 3142,
    "w1_20_39": 11789,
    "w1_40_59": 15877,
    "w1_60_69": 8613,
    "w1_70plus": 8258,
    "population": 85646,
    "atLeastOneDose": 48425,
    "fullyVaccinated": 47552
  },
  "0419": {
    "teryt": "0419",
    "w1_12_19": 2676,
    "w1_20_39": 9947,
    "w1_40_59": 12597,
    "w1_60_69": 7514,
    "w1_70plus": 7270,
    "population": 69886,
    "atLeastOneDose": 40756,
    "fullyVaccinated": 39911
  },
  "0461": {
    "teryt": "0461",
    "w1_12_19": 13996,
    "w1_20_39": 54838,
    "w1_40_59": 67005,
    "w1_60_69": 37840,
    "w1_70plus": 49271,
    "population": 344091,
    "atLeastOneDose": 228755,
    "fullyVaccinated": 224356
  },
  "0462": {
    "teryt": "0462",
    "w1_12_19": 3974,
    "w1_20_39": 12838,
    "w1_40_59": 17302,
    "w1_60_69": 11056,
    "w1_70plus": 11703,
    "population": 93564,
    "atLeastOneDose": 58197,
    "fullyVaccinated": 56912
  },
  "0463": {
    "teryt": "0463",
    "w1_12_19": 8785,
    "w1_20_39": 32555,
    "w1_40_59": 38294,
    "w1_60_69": 21992,
    "w1_70plus": 26010,
    "population": 198613,
    "atLeastOneDose": 131512,
    "fullyVaccinated": 128887
  },
  "0464": {
    "teryt": "0464",
    "w1_12_19": 3595,
    "w1_20_39": 12774,
    "w1_40_59": 19597,
    "w1_60_69": 12262,
    "w1_70plus": 14381,
    "population": 108561,
    "atLeastOneDose": 63588,
    "fullyVaccinated": 62421
  },
  "0601": {
    "teryt": "0601",
    "w1_12_19": 3068,
    "w1_20_39": 13288,
    "w1_40_59": 17048,
    "w1_60_69": 9380,
    "w1_70plus": 9593,
    "population": 109958,
    "atLeastOneDose": 52956,
    "fullyVaccinated": 51991
  },
  "0602": {
    "teryt": "0602",
    "w1_12_19": 1936,
    "w1_20_39": 10252,
    "w1_40_59": 13695,
    "w1_60_69": 8515,
    "w1_70plus": 9389,
    "population": 100333,
    "atLeastOneDose": 44036,
    "fullyVaccinated": 43154
  },
  "0603": {
    "teryt": "0603",
    "w1_12_19": 1983,
    "w1_20_39": 8570,
    "w1_40_59": 11797,
    "w1_60_69": 6916,
    "w1_70plus": 6465,
    "population": 77502,
    "atLeastOneDose": 36013,
    "fullyVaccinated": 35135
  },
  "0604": {
    "teryt": "0604",
    "w1_12_19": 1774,
    "w1_20_39": 7472,
    "w1_40_59": 10089,
    "w1_60_69": 6480,
    "w1_70plus": 7084,
    "population": 62009,
    "atLeastOneDose": 33175,
    "fullyVaccinated": 32494
  },
  "0605": {
    "teryt": "0605",
    "w1_12_19": 878,
    "w1_20_39": 4629,
    "w1_40_59": 6335,
    "w1_60_69": 3657,
    "w1_70plus": 4187,
    "population": 45142,
    "atLeastOneDose": 19798,
    "fullyVaccinated": 19411
  },
  "0606": {
    "teryt": "0606",
    "w1_12_19": 1501,
    "w1_20_39": 6820,
    "w1_40_59": 9527,
    "w1_60_69": 6334,
    "w1_70plus": 7427,
    "population": 62552,
    "atLeastOneDose": 31867,
    "fullyVaccinated": 31014
  },
  "0607": {
    "teryt": "0607",
    "w1_12_19": 2163,
    "w1_20_39": 9796,
    "w1_40_59": 13490,
    "w1_60_69": 8667,
    "w1_70plus": 10005,
    "population": 94531,
    "atLeastOneDose": 44494,
    "fullyVaccinated": 43425
  },
  "0608": {
    "teryt": "0608",
    "w1_12_19": 2095,
    "w1_20_39": 9248,
    "w1_40_59": 12311,
    "w1_60_69": 7080,
    "w1_70plus": 7831,
    "population": 87850,
    "atLeastOneDose": 38881,
    "fullyVaccinated": 37825
  },
  "0609": {
    "teryt": "0609",
    "w1_12_19": 5310,
    "w1_20_39": 20157,
    "w1_40_59": 28162,
    "w1_60_69": 13240,
    "w1_70plus": 13268,
    "population": 156493,
    "atLeastOneDose": 81449,
    "fullyVaccinated": 79667
  },
  "0610": {
    "teryt": "0610",
    "w1_12_19": 1360,
    "w1_20_39": 6318,
    "w1_40_59": 8256,
    "w1_60_69": 5299,
    "w1_70plus": 4164,
    "population": 57218,
    "atLeastOneDose": 25692,
    "fullyVaccinated": 25118
  },
  "0611": {
    "teryt": "0611",
    "w1_12_19": 2121,
    "w1_20_39": 12267,
    "w1_40_59": 14965,
    "w1_60_69": 8392,
    "w1_70plus": 9007,
    "population": 106213,
    "atLeastOneDose": 47073,
    "fullyVaccinated": 46027
  },
  "0612": {
    "teryt": "0612",
    "w1_12_19": 1656,
    "w1_20_39": 7052,
    "w1_40_59": 9091,
    "w1_60_69": 5644,
    "w1_70plus": 6125,
    "population": 58706,
    "atLeastOneDose": 29848,
    "fullyVaccinated": 29251
  },
  "0613": {
    "teryt": "0613",
    "w1_12_19": 802,
    "w1_20_39": 3948,
    "w1_40_59": 5045,
    "w1_60_69": 3258,
    "w1_70plus": 3405,
    "population": 34372,
    "atLeastOneDose": 16613,
    "fullyVaccinated": 16271
  },
  "0614": {
    "teryt": "0614",
    "w1_12_19": 3899,
    "w1_20_39": 14334,
    "w1_40_59": 19840,
    "w1_60_69": 11231,
    "w1_70plus": 14679,
    "population": 112384,
    "atLeastOneDose": 64744,
    "fullyVaccinated": 63357
  },
  "0615": {
    "teryt": "0615",
    "w1_12_19": 1134,
    "w1_20_39": 6161,
    "w1_40_59": 7928,
    "w1_60_69": 5023,
    "w1_70plus": 5052,
    "population": 58298,
    "atLeastOneDose": 25450,
    "fullyVaccinated": 24959
  },
  "0616": {
    "teryt": "0616",
    "w1_12_19": 1749,
    "w1_20_39": 7402,
    "w1_40_59": 9125,
    "w1_60_69": 5778,
    "w1_70plus": 6158,
    "population": 55530,
    "atLeastOneDose": 30508,
    "fullyVaccinated": 29805
  },
  "0617": {
    "teryt": "0617",
    "w1_12_19": 2233,
    "w1_20_39": 8392,
    "w1_40_59": 12072,
    "w1_60_69": 7024,
    "w1_70plus": 8602,
    "population": 71432,
    "atLeastOneDose": 38821,
    "fullyVaccinated": 37980
  },
  "0618": {
    "teryt": "0618",
    "w1_12_19": 1736,
    "w1_20_39": 9095,
    "w1_40_59": 12647,
    "w1_60_69": 8150,
    "w1_70plus": 8557,
    "population": 81944,
    "atLeastOneDose": 40446,
    "fullyVaccinated": 39503
  },
  "0619": {
    "teryt": "0619",
    "w1_12_19": 1283,
    "w1_20_39": 4499,
    "w1_40_59": 6233,
    "w1_60_69": 3879,
    "w1_70plus": 3981,
    "population": 37989,
    "atLeastOneDose": 20147,
    "fullyVaccinated": 19766
  },
  "0620": {
    "teryt": "0620",
    "w1_12_19": 2540,
    "w1_20_39": 12103,
    "w1_40_59": 15863,
    "w1_60_69": 9316,
    "w1_70plus": 10053,
    "population": 105354,
    "atLeastOneDose": 50264,
    "fullyVaccinated": 49043
  },
  "0661": {
    "teryt": "0661",
    "w1_12_19": 1739,
    "w1_20_39": 7865,
    "w1_40_59": 9655,
    "w1_60_69": 6275,
    "w1_70plus": 5510,
    "population": 56942,
    "atLeastOneDose": 31443,
    "fullyVaccinated": 30818
  },
  "0662": {
    "teryt": "0662",
    "w1_12_19": 1713,
    "w1_20_39": 7091,
    "w1_40_59": 10602,
    "w1_60_69": 7233,
    "w1_70plus": 7272,
    "population": 61135,
    "atLeastOneDose": 34318,
    "fullyVaccinated": 33565
  },
  "0663": {
    "teryt": "0663",
    "w1_12_19": 12870,
    "w1_20_39": 54233,
    "w1_40_59": 61764,
    "w1_60_69": 33894,
    "w1_70plus": 44021,
    "population": 338586,
    "atLeastOneDose": 211145,
    "fullyVaccinated": 206652
  },
  "0664": {
    "teryt": "0664",
    "w1_12_19": 1867,
    "w1_20_39": 7515,
    "w1_40_59": 9989,
    "w1_60_69": 7338,
    "w1_70plus": 7167,
    "population": 62785,
    "atLeastOneDose": 34265,
    "fullyVaccinated": 33485
  },
  "0801": {
    "teryt": "0801",
    "w1_12_19": 3044,
    "w1_20_39": 11241,
    "w1_40_59": 14707,
    "w1_60_69": 7377,
    "w1_70plus": 6077,
    "population": 72291,
    "atLeastOneDose": 43178,
    "fullyVaccinated": 42046
  },
  "0802": {
    "teryt": "0802",
    "w1_12_19": 1958,
    "w1_20_39": 8517,
    "w1_40_59": 10666,
    "w1_60_69": 5924,
    "w1_70plus": 5655,
    "population": 54598,
    "atLeastOneDose": 33151,
    "fullyVaccinated": 32345
  },
  "0803": {
    "teryt": "0803",
    "w1_12_19": 2319,
    "w1_20_39": 8836,
    "w1_40_59": 11250,
    "w1_60_69": 6496,
    "w1_70plus": 6180,
    "population": 57100,
    "atLeastOneDose": 35726,
    "fullyVaccinated": 34815
  },
  "0804": {
    "teryt": "0804",
    "w1_12_19": 3331,
    "w1_20_39": 12011,
    "w1_40_59": 15258,
    "w1_60_69": 9133,
    "w1_70plus": 9601,
    "population": 85733,
    "atLeastOneDose": 50286,
    "fullyVaccinated": 49140
  },
  "0805": {
    "teryt": "0805",
    "w1_12_19": 2160,
    "w1_20_39": 8497,
    "w1_40_59": 10504,
    "w1_60_69": 5050,
    "w1_70plus": 4282,
    "population": 46944,
    "atLeastOneDose": 31027,
    "fullyVaccinated": 30258
  },
  "0806": {
    "teryt": "0806",
    "w1_12_19": 2014,
    "w1_20_39": 7061,
    "w1_40_59": 9037,
    "w1_60_69": 5389,
    "w1_70plus": 5250,
    "population": 48621,
    "atLeastOneDose": 29329,
    "fullyVaccinated": 28737
  },
  "0807": {
    "teryt": "0807",
    "w1_12_19": 1430,
    "w1_20_39": 5695,
    "w1_40_59": 6806,
    "w1_60_69": 3808,
    "w1_70plus": 3357,
    "population": 35000,
    "atLeastOneDose": 21506,
    "fullyVaccinated": 21042
  },
  "0808": {
    "teryt": "0808",
    "w1_12_19": 2159,
    "w1_20_39": 8596,
    "w1_40_59": 10664,
    "w1_60_69": 6054,
    "w1_70plus": 5767,
    "population": 55520,
    "atLeastOneDose": 33910,
    "fullyVaccinated": 33081
  },
  "0809": {
    "teryt": "0809",
    "w1_12_19": 3083,
    "w1_20_39": 11703,
    "w1_40_59": 15011,
    "w1_60_69": 8273,
    "w1_70plus": 7591,
    "population": 75673,
    "atLeastOneDose": 46490,
    "fullyVaccinated": 45456
  },
  "0810": {
    "teryt": "0810",
    "w1_12_19": 2825,
    "w1_20_39": 10842,
    "w1_40_59": 14189,
    "w1_60_69": 8617,
    "w1_70plus": 8252,
    "population": 78148,
    "atLeastOneDose": 45485,
    "fullyVaccinated": 44522
  },
  "0811": {
    "teryt": "0811",
    "w1_12_19": 3778,
    "w1_20_39": 14082,
    "w1_40_59": 18424,
    "w1_60_69": 10494,
    "w1_70plus": 9956,
    "population": 95423,
    "atLeastOneDose": 57827,
    "fullyVaccinated": 56688
  },
  "0812": {
    "teryt": "0812",
    "w1_12_19": 1328,
    "w1_20_39": 4961,
    "w1_40_59": 6563,
    "w1_60_69": 3857,
    "w1_70plus": 3689,
    "population": 38613,
    "atLeastOneDose": 20729,
    "fullyVaccinated": 20268
  },
  "0861": {
    "teryt": "0861",
    "w1_12_19": 4901,
    "w1_20_39": 19169,
    "w1_40_59": 24593,
    "w1_60_69": 13862,
    "w1_70plus": 15520,
    "population": 122589,
    "atLeastOneDose": 79479,
    "fullyVaccinated": 77240
  },
  "0862": {
    "teryt": "0862",
    "w1_12_19": 6185,
    "w1_20_39": 23275,
    "w1_40_59": 29311,
    "w1_60_69": 15303,
    "w1_70plus": 18105,
    "population": 140892,
    "atLeastOneDose": 94566,
    "fullyVaccinated": 92750
  },
  "1001": {
    "teryt": "1001",
    "w1_12_19": 2828,
    "w1_20_39": 13047,
    "w1_40_59": 18016,
    "w1_60_69": 12716,
    "w1_70plus": 9512,
    "population": 112443,
    "atLeastOneDose": 56768,
    "fullyVaccinated": 55677
  },
  "1002": {
    "teryt": "1002",
    "w1_12_19": 3278,
    "w1_20_39": 12886,
    "w1_40_59": 18701,
    "w1_60_69": 11298,
    "w1_70plus": 11993,
    "population": 95516,
    "atLeastOneDose": 59074,
    "fullyVaccinated": 57738
  },
  "1003": {
    "teryt": "1003",
    "w1_12_19": 1492,
    "w1_20_39": 6081,
    "w1_40_59": 8725,
    "w1_60_69": 5138,
    "w1_70plus": 5430,
    "population": 49736,
    "atLeastOneDose": 27202,
    "fullyVaccinated": 26765
  },
  "1004": {
    "teryt": "1004",
    "w1_12_19": 1694,
    "w1_20_39": 6641,
    "w1_40_59": 9000,
    "w1_60_69": 5326,
    "w1_70plus": 5884,
    "population": 49286,
    "atLeastOneDose": 28930,
    "fullyVaccinated": 28333
  },
  "1005": {
    "teryt": "1005",
    "w1_12_19": 2868,
    "w1_20_39": 11071,
    "w1_40_59": 14778,
    "w1_60_69": 8555,
    "w1_70plus": 9164,
    "population": 77614,
    "atLeastOneDose": 47209,
    "fullyVaccinated": 46223
  },
  "1006": {
    "teryt": "1006",
    "w1_12_19": 2915,
    "w1_20_39": 10104,
    "w1_40_59": 14847,
    "w1_60_69": 7282,
    "w1_70plus": 7395,
    "population": 72565,
    "atLeastOneDose": 43399,
    "fullyVaccinated": 42603
  },
  "1007": {
    "teryt": "1007",
    "w1_12_19": 2497,
    "w1_20_39": 10551,
    "w1_40_59": 13110,
    "w1_60_69": 7404,
    "w1_70plus": 7420,
    "population": 75524,
    "atLeastOneDose": 41479,
    "fullyVaccinated": 40661
  },
  "1008": {
    "teryt": "1008",
    "w1_12_19": 4295,
    "w1_20_39": 15998,
    "w1_40_59": 23118,
    "w1_60_69": 12636,
    "w1_70plus": 15331,
    "population": 118941,
    "atLeastOneDose": 72929,
    "fullyVaccinated": 71360
  },
  "1009": {
    "teryt": "1009",
    "w1_12_19": 1285,
    "w1_20_39": 6166,
    "w1_40_59": 8390,
    "w1_60_69": 4808,
    "w1_70plus": 5279,
    "population": 50952,
    "atLeastOneDose": 26132,
    "fullyVaccinated": 25573
  },
  "1010": {
    "teryt": "1010",
    "w1_12_19": 3023,
    "w1_20_39": 12123,
    "w1_40_59": 16364,
    "w1_60_69": 8555,
    "w1_70plus": 9029,
    "population": 91208,
    "atLeastOneDose": 49633,
    "fullyVaccinated": 48532
  },
  "1011": {
    "teryt": "1011",
    "w1_12_19": 1270,
    "w1_20_39": 5434,
    "w1_40_59": 7576,
    "w1_60_69": 4201,
    "w1_70plus": 4634,
    "population": 40906,
    "atLeastOneDose": 23398,
    "fullyVaccinated": 22872
  },
  "1012": {
    "teryt": "1012",
    "w1_12_19": 3582,
    "w1_20_39": 14362,
    "w1_40_59": 19752,
    "w1_60_69": 10994,
    "w1_70plus": 12555,
    "population": 111696,
    "atLeastOneDose": 61916,
    "fullyVaccinated": 60471
  },
  "1013": {
    "teryt": "1013",
    "w1_12_19": 1453,
    "w1_20_39": 6272,
    "w1_40_59": 8075,
    "w1_60_69": 4739,
    "w1_70plus": 4933,
    "population": 48385,
    "atLeastOneDose": 25728,
    "fullyVaccinated": 25173
  },
  "1014": {
    "teryt": "1014",
    "w1_12_19": 3407,
    "w1_20_39": 15394,
    "w1_40_59": 20689,
    "w1_60_69": 11754,
    "w1_70plus": 12792,
    "population": 116918,
    "atLeastOneDose": 64747,
    "fullyVaccinated": 63487
  },
  "1015": {
    "teryt": "1015",
    "w1_12_19": 1227,
    "w1_20_39": 5074,
    "w1_40_59": 6349,
    "w1_60_69": 3461,
    "w1_70plus": 3737,
    "population": 38173,
    "atLeastOneDose": 20108,
    "fullyVaccinated": 19708
  },
  "1016": {
    "teryt": "1016",
    "w1_12_19": 3713,
    "w1_20_39": 14826,
    "w1_40_59": 20480,
    "w1_60_69": 11939,
    "w1_70plus": 13215,
    "population": 115735,
    "atLeastOneDose": 64925,
    "fullyVaccinated": 63660
  },
  "1017": {
    "teryt": "1017",
    "w1_12_19": 2509,
    "w1_20_39": 10070,
    "w1_40_59": 13837,
    "w1_60_69": 7975,
    "w1_70plus": 8419,
    "population": 75736,
    "atLeastOneDose": 43355,
    "fullyVaccinated": 42491
  },
  "1018": {
    "teryt": "1018",
    "w1_12_19": 1278,
    "w1_20_39": 5722,
    "w1_40_59": 7553,
    "w1_60_69": 3994,
    "w1_70plus": 4203,
    "population": 41984,
    "atLeastOneDose": 23032,
    "fullyVaccinated": 22699
  },
  "1019": {
    "teryt": "1019",
    "w1_12_19": 2120,
    "w1_20_39": 8082,
    "w1_40_59": 11406,
    "w1_60_69": 6766,
    "w1_70plus": 7391,
    "population": 66064,
    "atLeastOneDose": 36268,
    "fullyVaccinated": 35591
  },
  "1020": {
    "teryt": "1020",
    "w1_12_19": 6541,
    "w1_20_39": 24105,
    "w1_40_59": 34234,
    "w1_60_69": 17589,
    "w1_70plus": 19949,
    "population": 165850,
    "atLeastOneDose": 104667,
    "fullyVaccinated": 102129
  },
  "1021": {
    "teryt": "1021",
    "w1_12_19": 991,
    "w1_20_39": 3977,
    "w1_40_59": 5533,
    "w1_60_69": 2940,
    "w1_70plus": 3244,
    "population": 30648,
    "atLeastOneDose": 16987,
    "fullyVaccinated": 16641
  },
  "1061": {
    "teryt": "1061",
    "w1_12_19": 26072,
    "w1_20_39": 108519,
    "w1_40_59": 131415,
    "w1_60_69": 78930,
    "w1_70plus": 103610,
    "population": 672185,
    "atLeastOneDose": 459861,
    "fullyVaccinated": 449476
  },
  "1062": {
    "teryt": "1062",
    "w1_12_19": 2781,
    "w1_20_39": 10047,
    "w1_40_59": 14010,
    "w1_60_69": 8023,
    "w1_70plus": 9523,
    "population": 72250,
    "atLeastOneDose": 45125,
    "fullyVaccinated": 44263
  },
  "1063": {
    "teryt": "1063",
    "w1_12_19": 2041,
    "w1_20_39": 7148,
    "w1_40_59": 9572,
    "w1_60_69": 5732,
    "w1_70plus": 5881,
    "population": 47655,
    "atLeastOneDose": 31099,
    "fullyVaccinated": 30468
  },
  "1201": {
    "teryt": "1201",
    "w1_12_19": 3483,
    "w1_20_39": 15568,
    "w1_40_59": 18459,
    "w1_60_69": 9231,
    "w1_70plus": 9144,
    "population": 106947,
    "atLeastOneDose": 56761,
    "fullyVaccinated": 55655
  },
  "1202": {
    "teryt": "1202",
    "w1_12_19": 2335,
    "w1_20_39": 11852,
    "w1_40_59": 14068,
    "w1_60_69": 7385,
    "w1_70plus": 7589,
    "population": 93035,
    "atLeastOneDose": 43706,
    "fullyVaccinated": 42879
  },
  "1203": {
    "teryt": "1203",
    "w1_12_19": 4417,
    "w1_20_39": 17284,
    "w1_40_59": 23759,
    "w1_60_69": 14067,
    "w1_70plus": 14720,
    "population": 123664,
    "atLeastOneDose": 75621,
    "fullyVaccinated": 74287
  },
  "1204": {
    "teryt": "1204",
    "w1_12_19": 1019,
    "w1_20_39": 6092,
    "w1_40_59": 7579,
    "w1_60_69": 4066,
    "w1_70plus": 4460,
    "population": 58977,
    "atLeastOneDose": 23388,
    "fullyVaccinated": 22828
  },
  "1205": {
    "teryt": "1205",
    "w1_12_19": 2235,
    "w1_20_39": 12165,
    "w1_40_59": 15110,
    "w1_60_69": 8858,
    "w1_70plus": 9092,
    "population": 108487,
    "atLeastOneDose": 47834,
    "fullyVaccinated": 46911
  },
  "1206": {
    "teryt": "1206",
    "w1_12_19": 12584,
    "w1_20_39": 47258,
    "w1_40_59": 59681,
    "w1_60_69": 27311,
    "w1_70plus": 26518,
    "population": 281440,
    "atLeastOneDose": 177672,
    "fullyVaccinated": 174270
  },
  "1207": {
    "teryt": "1207",
    "w1_12_19": 2848,
    "w1_20_39": 17063,
    "w1_40_59": 18356,
    "w1_60_69": 8555,
    "w1_70plus": 8305,
    "population": 132148,
    "atLeastOneDose": 55596,
    "fullyVaccinated": 54467
  },
  "1208": {
    "teryt": "1208",
    "w1_12_19": 1676,
    "w1_20_39": 7218,
    "w1_40_59": 9256,
    "w1_60_69": 5197,
    "w1_70plus": 5948,
    "population": 48464,
    "atLeastOneDose": 29741,
    "fullyVaccinated": 29010
  },
  "1209": {
    "teryt": "1209",
    "w1_12_19": 4379,
    "w1_20_39": 19415,
    "w1_40_59": 22044,
    "w1_60_69": 10634,
    "w1_70plus": 9409,
    "population": 127972,
    "atLeastOneDose": 66888,
    "fullyVaccinated": 65793
  },
  "1210": {
    "teryt": "1210",
    "w1_12_19": 5029,
    "w1_20_39": 28130,
    "w1_40_59": 31886,
    "w1_60_69": 15156,
    "w1_70plus": 14216,
    "population": 217071,
    "atLeastOneDose": 95242,
    "fullyVaccinated": 93398
  },
  "1211": {
    "teryt": "1211",
    "w1_12_19": 4035,
    "w1_20_39": 21490,
    "w1_40_59": 24350,
    "w1_60_69": 12048,
    "w1_70plus": 13347,
    "population": 191646,
    "atLeastOneDose": 75922,
    "fullyVaccinated": 74460
  },
  "1212": {
    "teryt": "1212",
    "w1_12_19": 4057,
    "w1_20_39": 15561,
    "w1_40_59": 21164,
    "w1_60_69": 12591,
    "w1_70plus": 13373,
    "population": 110471,
    "atLeastOneDose": 67862,
    "fullyVaccinated": 66373
  },
  "1213": {
    "teryt": "1213",
    "w1_12_19": 5868,
    "w1_20_39": 21875,
    "w1_40_59": 29564,
    "w1_60_69": 16628,
    "w1_70plus": 18008,
    "population": 152687,
    "atLeastOneDose": 93616,
    "fullyVaccinated": 91951
  },
  "1214": {
    "teryt": "1214",
    "w1_12_19": 1473,
    "w1_20_39": 6319,
    "w1_40_59": 7716,
    "w1_60_69": 4168,
    "w1_70plus": 4459,
    "population": 43057,
    "atLeastOneDose": 24472,
    "fullyVaccinated": 23976
  },
  "1215": {
    "teryt": "1215",
    "w1_12_19": 3051,
    "w1_20_39": 12750,
    "w1_40_59": 14861,
    "w1_60_69": 7435,
    "w1_70plus": 7738,
    "population": 83761,
    "atLeastOneDose": 46445,
    "fullyVaccinated": 45573
  },
  "1216": {
    "teryt": "1216",
    "w1_12_19": 4645,
    "w1_20_39": 24618,
    "w1_40_59": 29808,
    "w1_60_69": 14643,
    "w1_70plus": 15068,
    "population": 201230,
    "atLeastOneDose": 89607,
    "fullyVaccinated": 87774
  },
  "1217": {
    "teryt": "1217",
    "w1_12_19": 1537,
    "w1_20_39": 7530,
    "w1_40_59": 8900,
    "w1_60_69": 4691,
    "w1_70plus": 5135,
    "population": 68049,
    "atLeastOneDose": 28177,
    "fullyVaccinated": 27596
  },
  "1218": {
    "teryt": "1218",
    "w1_12_19": 5500,
    "w1_20_39": 22923,
    "w1_40_59": 29153,
    "w1_60_69": 14853,
    "w1_70plus": 14498,
    "population": 159662,
    "atLeastOneDose": 88161,
    "fullyVaccinated": 86542
  },
  "1219": {
    "teryt": "1219",
    "w1_12_19": 5560,
    "w1_20_39": 21769,
    "w1_40_59": 27055,
    "w1_60_69": 11649,
    "w1_70plus": 10703,
    "population": 130651,
    "atLeastOneDose": 78695,
    "fullyVaccinated": 77220
  },
  "1261": {
    "teryt": "1261",
    "w1_12_19": 33389,
    "w1_20_39": 182090,
    "w1_40_59": 160067,
    "w1_60_69": 73957,
    "w1_70plus": 101166,
    "population": 779966,
    "atLeastOneDose": 567015,
    "fullyVaccinated": 555368
  },
  "1262": {
    "teryt": "1262",
    "w1_12_19": 2341,
    "w1_20_39": 10494,
    "w1_40_59": 13720,
    "w1_60_69": 7752,
    "w1_70plus": 8667,
    "population": 83558,
    "atLeastOneDose": 43446,
    "fullyVaccinated": 42619
  },
  "1263": {
    "teryt": "1263",
    "w1_12_19": 3261,
    "w1_20_39": 13391,
    "w1_40_59": 17770,
    "w1_60_69": 10754,
    "w1_70plus": 14076,
    "population": 107498,
    "atLeastOneDose": 60146,
    "fullyVaccinated": 59085
  },
  "1401": {
    "teryt": "1401",
    "w1_12_19": 1197,
    "w1_20_39": 4893,
    "w1_40_59": 5826,
    "w1_60_69": 3096,
    "w1_70plus": 3022,
    "population": 33329,
    "atLeastOneDose": 18336,
    "fullyVaccinated": 17883
  },
  "1402": {
    "teryt": "1402",
    "w1_12_19": 2837,
    "w1_20_39": 12718,
    "w1_40_59": 15943,
    "w1_60_69": 10130,
    "w1_70plus": 8945,
    "population": 88891,
    "atLeastOneDose": 51208,
    "fullyVaccinated": 49713
  },
  "1403": {
    "teryt": "1403",
    "w1_12_19": 3881,
    "w1_20_39": 16254,
    "w1_40_59": 19207,
    "w1_60_69": 9664,
    "w1_70plus": 9523,
    "population": 108634,
    "atLeastOneDose": 59313,
    "fullyVaccinated": 57925
  },
  "1404": {
    "teryt": "1404",
    "w1_12_19": 1303,
    "w1_20_39": 5507,
    "w1_40_59": 7673,
    "w1_60_69": 4525,
    "w1_70plus": 4932,
    "population": 44581,
    "atLeastOneDose": 24226,
    "fullyVaccinated": 23772
  },
  "1405": {
    "teryt": "1405",
    "w1_12_19": 4860,
    "w1_20_39": 15878,
    "w1_40_59": 21317,
    "w1_60_69": 9284,
    "w1_70plus": 9718,
    "population": 97462,
    "atLeastOneDose": 62901,
    "fullyVaccinated": 61498
  },
  "1406": {
    "teryt": "1406",
    "w1_12_19": 3671,
    "w1_20_39": 13667,
    "w1_40_59": 18562,
    "w1_60_69": 10007,
    "w1_70plus": 10132,
    "population": 97979,
    "atLeastOneDose": 56947,
    "fullyVaccinated": 55620
  },
  "1407": {
    "teryt": "1407",
    "w1_12_19": 1590,
    "w1_20_39": 7391,
    "w1_40_59": 9684,
    "w1_60_69": 6434,
    "w1_70plus": 6144,
    "population": 59592,
    "atLeastOneDose": 31555,
    "fullyVaccinated": 30967
  },
  "1408": {
    "teryt": "1408",
    "w1_12_19": 6916,
    "w1_20_39": 19693,
    "w1_40_59": 28343,
    "w1_60_69": 11680,
    "w1_70plus": 12508,
    "population": 119882,
    "atLeastOneDose": 81539,
    "fullyVaccinated": 79659
  },
  "1409": {
    "teryt": "1409",
    "w1_12_19": 686,
    "w1_20_39": 3908,
    "w1_40_59": 5082,
    "w1_60_69": 3397,
    "w1_70plus": 3613,
    "population": 33598,
    "atLeastOneDose": 16785,
    "fullyVaccinated": 16437
  },
  "1410": {
    "teryt": "1410",
    "w1_12_19": 600,
    "w1_20_39": 3301,
    "w1_40_59": 4235,
    "w1_60_69": 2745,
    "w1_70plus": 3144,
    "population": 30556,
    "atLeastOneDose": 14110,
    "fullyVaccinated": 13785
  },
  "1411": {
    "teryt": "1411",
    "w1_12_19": 1542,
    "w1_20_39": 6154,
    "w1_40_59": 7602,
    "w1_60_69": 4709,
    "w1_70plus": 4496,
    "population": 44438,
    "atLeastOneDose": 24844,
    "fullyVaccinated": 24265
  },
  "1412": {
    "teryt": "1412",
    "w1_12_19": 6773,
    "w1_20_39": 24233,
    "w1_40_59": 31120,
    "w1_60_69": 14643,
    "w1_70plus": 14839,
    "population": 154951,
    "atLeastOneDose": 93631,
    "fullyVaccinated": 91463
  },
  "1413": {
    "teryt": "1413",
    "w1_12_19": 2199,
    "w1_20_39": 10928,
    "w1_40_59": 13184,
    "w1_60_69": 7214,
    "w1_70plus": 6770,
    "population": 72269,
    "atLeastOneDose": 40760,
    "fullyVaccinated": 39551
  },
  "1414": {
    "teryt": "1414",
    "w1_12_19": 3322,
    "w1_20_39": 12896,
    "w1_40_59": 16356,
    "w1_60_69": 8669,
    "w1_70plus": 7831,
    "population": 79265,
    "atLeastOneDose": 50131,
    "fullyVaccinated": 48767
  },
  "1415": {
    "teryt": "1415",
    "w1_12_19": 2301,
    "w1_20_39": 10217,
    "w1_40_59": 13186,
    "w1_60_69": 6821,
    "w1_70plus": 6194,
    "population": 88497,
    "atLeastOneDose": 39109,
    "fullyVaccinated": 38197
  },
  "1416": {
    "teryt": "1416",
    "w1_12_19": 1982,
    "w1_20_39": 8626,
    "w1_40_59": 11486,
    "w1_60_69": 6659,
    "w1_70plus": 7050,
    "population": 71790,
    "atLeastOneDose": 36127,
    "fullyVaccinated": 35099
  },
  "1417": {
    "teryt": "1417",
    "w1_12_19": 6013,
    "w1_20_39": 19459,
    "w1_40_59": 26653,
    "w1_60_69": 12742,
    "w1_70plus": 14052,
    "population": 124283,
    "atLeastOneDose": 80825,
    "fullyVaccinated": 78895
  },
  "1418": {
    "teryt": "1418",
    "w1_12_19": 12681,
    "w1_20_39": 35529,
    "w1_40_59": 48833,
    "w1_60_69": 17811,
    "w1_70plus": 18335,
    "population": 190606,
    "atLeastOneDose": 138038,
    "fullyVaccinated": 134792
  },
  "1419": {
    "teryt": "1419",
    "w1_12_19": 3939,
    "w1_20_39": 15135,
    "w1_40_59": 21090,
    "w1_60_69": 9970,
    "w1_70plus": 9965,
    "population": 110742,
    "atLeastOneDose": 60898,
    "fullyVaccinated": 59771
  },
  "1420": {
    "teryt": "1420",
    "w1_12_19": 2625,
    "w1_20_39": 11906,
    "w1_40_59": 15375,
    "w1_60_69": 8577,
    "w1_70plus": 8274,
    "population": 86671,
    "atLeastOneDose": 47297,
    "fullyVaccinated": 46162
  },
  "1421": {
    "teryt": "1421",
    "w1_12_19": 9291,
    "w1_20_39": 31870,
    "w1_40_59": 40684,
    "w1_60_69": 17053,
    "w1_70plus": 19266,
    "population": 166679,
    "atLeastOneDose": 122209,
    "fullyVaccinated": 119494
  },
  "1422": {
    "teryt": "1422",
    "w1_12_19": 1668,
    "w1_20_39": 6790,
    "w1_40_59": 8577,
    "w1_60_69": 5097,
    "w1_70plus": 4785,
    "population": 52101,
    "atLeastOneDose": 27255,
    "fullyVaccinated": 26517
  },
  "1423": {
    "teryt": "1423",
    "w1_12_19": 1279,
    "w1_20_39": 5795,
    "w1_40_59": 7242,
    "w1_60_69": 4185,
    "w1_70plus": 4386,
    "population": 41126,
    "atLeastOneDose": 23119,
    "fullyVaccinated": 22622
  },
  "1424": {
    "teryt": "1424",
    "w1_12_19": 1916,
    "w1_20_39": 7767,
    "w1_40_59": 9441,
    "w1_60_69": 5045,
    "w1_70plus": 4872,
    "population": 51741,
    "atLeastOneDose": 29464,
    "fullyVaccinated": 28778
  },
  "1425": {
    "teryt": "1425",
    "w1_12_19": 4109,
    "w1_20_39": 18698,
    "w1_40_59": 24128,
    "w1_60_69": 13176,
    "w1_70plus": 12032,
    "population": 152190,
    "atLeastOneDose": 72708,
    "fullyVaccinated": 71175
  },
  "1426": {
    "teryt": "1426",
    "w1_12_19": 1520,
    "w1_20_39": 8518,
    "w1_40_59": 11403,
    "w1_60_69": 6017,
    "w1_70plus": 6403,
    "population": 81385,
    "atLeastOneDose": 34129,
    "fullyVaccinated": 33418
  },
  "1427": {
    "teryt": "1427",
    "w1_12_19": 1672,
    "w1_20_39": 6940,
    "w1_40_59": 8859,
    "w1_60_69": 5020,
    "w1_70plus": 4983,
    "population": 51534,
    "atLeastOneDose": 27792,
    "fullyVaccinated": 27198
  },
  "1428": {
    "teryt": "1428",
    "w1_12_19": 3246,
    "w1_20_39": 13046,
    "w1_40_59": 16311,
    "w1_60_69": 8706,
    "w1_70plus": 8534,
    "population": 84804,
    "atLeastOneDose": 50700,
    "fullyVaccinated": 49548
  },
  "1429": {
    "teryt": "1429",
    "w1_12_19": 1489,
    "w1_20_39": 6746,
    "w1_40_59": 8927,
    "w1_60_69": 5657,
    "w1_70plus": 5959,
    "population": 53294,
    "atLeastOneDose": 29164,
    "fullyVaccinated": 28568
  },
  "1430": {
    "teryt": "1430",
    "w1_12_19": 878,
    "w1_20_39": 4811,
    "w1_40_59": 5905,
    "w1_60_69": 3556,
    "w1_70plus": 3370,
    "population": 39340,
    "atLeastOneDose": 18647,
    "fullyVaccinated": 18213
  },
  "1432": {
    "teryt": "1432",
    "w1_12_19": 7060,
    "w1_20_39": 21827,
    "w1_40_59": 28900,
    "w1_60_69": 12432,
    "w1_70plus": 12198,
    "population": 120144,
    "atLeastOneDose": 85021,
    "fullyVaccinated": 83111
  },
  "1433": {
    "teryt": "1433",
    "w1_12_19": 1907,
    "w1_20_39": 8388,
    "w1_40_59": 10895,
    "w1_60_69": 6174,
    "w1_70plus": 6589,
    "population": 65410,
    "atLeastOneDose": 34400,
    "fullyVaccinated": 33642
  },
  "1434": {
    "teryt": "1434",
    "w1_12_19": 11832,
    "w1_20_39": 41822,
    "w1_40_59": 53554,
    "w1_60_69": 21178,
    "w1_70plus": 20676,
    "population": 252408,
    "atLeastOneDose": 152901,
    "fullyVaccinated": 149023
  },
  "1435": {
    "teryt": "1435",
    "w1_12_19": 2499,
    "w1_20_39": 10329,
    "w1_40_59": 13493,
    "w1_60_69": 7009,
    "w1_70plus": 6723,
    "population": 74210,
    "atLeastOneDose": 40660,
    "fullyVaccinated": 39857
  },
  "1436": {
    "teryt": "1436",
    "w1_12_19": 829,
    "w1_20_39": 4219,
    "w1_40_59": 5233,
    "w1_60_69": 3089,
    "w1_70plus": 3170,
    "population": 35875,
    "atLeastOneDose": 16670,
    "fullyVaccinated": 16331
  },
  "1437": {
    "teryt": "1437",
    "w1_12_19": 1310,
    "w1_20_39": 5505,
    "w1_40_59": 7009,
    "w1_60_69": 3826,
    "w1_70plus": 3926,
    "population": 38202,
    "atLeastOneDose": 21845,
    "fullyVaccinated": 21403
  },
  "1438": {
    "teryt": "1438",
    "w1_12_19": 2786,
    "w1_20_39": 10839,
    "w1_40_59": 14242,
    "w1_60_69": 7530,
    "w1_70plus": 8002,
    "population": 75370,
    "atLeastOneDose": 44170,
    "fullyVaccinated": 42904
  },
  "1461": {
    "teryt": "1461",
    "w1_12_19": 1603,
    "w1_20_39": 6589,
    "w1_40_59": 8614,
    "w1_60_69": 5995,
    "w1_70plus": 5566,
    "population": 51656,
    "atLeastOneDose": 28776,
    "fullyVaccinated": 28139
  },
  "1462": {
    "teryt": "1462",
    "w1_12_19": 4673,
    "w1_20_39": 16079,
    "w1_40_59": 24114,
    "w1_60_69": 13190,
    "w1_70plus": 16271,
    "population": 118268,
    "atLeastOneDose": 75768,
    "fullyVaccinated": 74453
  },
  "1463": {
    "teryt": "1463",
    "w1_12_19": 6635,
    "w1_20_39": 26505,
    "w1_40_59": 36246,
    "w1_60_69": 23095,
    "w1_70plus": 25202,
    "population": 209296,
    "atLeastOneDose": 119000,
    "fullyVaccinated": 116671
  },
  "1464": {
    "teryt": "1464",
    "w1_12_19": 2219,
    "w1_20_39": 9953,
    "w1_40_59": 12505,
    "w1_60_69": 7607,
    "w1_70plus": 8179,
    "population": 77813,
    "atLeastOneDose": 40945,
    "fullyVaccinated": 40127
  },
  "1465": {
    "teryt": "1465",
    "w1_12_19": 94072,
    "w1_20_39": 412602,
    "w1_40_59": 415961,
    "w1_60_69": 176866,
    "w1_70plus": 244806,
    "population": 1794166,
    "atLeastOneDose": 1395309,
    "fullyVaccinated": 1363273
  },
  "1601": {
    "teryt": "1601",
    "w1_12_19": 2831,
    "w1_20_39": 11001,
    "w1_40_59": 14409,
    "w1_60_69": 8880,
    "w1_70plus": 9545,
    "population": 89282,
    "atLeastOneDose": 47446,
    "fullyVaccinated": 46201
  },
  "1602": {
    "teryt": "1602",
    "w1_12_19": 1167,
    "w1_20_39": 5229,
    "w1_40_59": 7202,
    "w1_60_69": 4719,
    "w1_70plus": 4980,
    "population": 45015,
    "atLeastOneDose": 23521,
    "fullyVaccinated": 23014
  },
  "1603": {
    "teryt": "1603",
    "w1_12_19": 2824,
    "w1_20_39": 11180,
    "w1_40_59": 14926,
    "w1_60_69": 8637,
    "w1_70plus": 10628,
    "population": 93001,
    "atLeastOneDose": 49030,
    "fullyVaccinated": 47939
  },
  "1604": {
    "teryt": "1604",
    "w1_12_19": 2012,
    "w1_20_39": 7970,
    "w1_40_59": 10293,
    "w1_60_69": 6291,
    "w1_70plus": 7010,
    "population": 65026,
    "atLeastOneDose": 34140,
    "fullyVaccinated": 33398
  },
  "1605": {
    "teryt": "1605",
    "w1_12_19": 1973,
    "w1_20_39": 8037,
    "w1_40_59": 9903,
    "w1_60_69": 5572,
    "w1_70plus": 6094,
    "population": 63196,
    "atLeastOneDose": 32185,
    "fullyVaccinated": 31615
  },
  "1606": {
    "teryt": "1606",
    "w1_12_19": 1552,
    "w1_20_39": 5573,
    "w1_40_59": 7186,
    "w1_60_69": 4470,
    "w1_70plus": 4483,
    "population": 42543,
    "atLeastOneDose": 23750,
    "fullyVaccinated": 23261
  },
  "1607": {
    "teryt": "1607",
    "w1_12_19": 4243,
    "w1_20_39": 16751,
    "w1_40_59": 22769,
    "w1_60_69": 14679,
    "w1_70plus": 15868,
    "population": 134864,
    "atLeastOneDose": 75397,
    "fullyVaccinated": 73671
  },
  "1608": {
    "teryt": "1608",
    "w1_12_19": 1593,
    "w1_20_39": 7146,
    "w1_40_59": 9031,
    "w1_60_69": 5720,
    "w1_70plus": 6285,
    "population": 63788,
    "atLeastOneDose": 30180,
    "fullyVaccinated": 29530
  },
  "1609": {
    "teryt": "1609",
    "w1_12_19": 3772,
    "w1_20_39": 15106,
    "w1_40_59": 19951,
    "w1_60_69": 10726,
    "w1_70plus": 11304,
    "population": 123532,
    "atLeastOneDose": 61975,
    "fullyVaccinated": 60798
  },
  "1610": {
    "teryt": "1610",
    "w1_12_19": 1540,
    "w1_20_39": 6403,
    "w1_40_59": 7852,
    "w1_60_69": 5054,
    "w1_70plus": 5781,
    "population": 54765,
    "atLeastOneDose": 27057,
    "fullyVaccinated": 26486
  },
  "1611": {
    "teryt": "1611",
    "w1_12_19": 2177,
    "w1_20_39": 9494,
    "w1_40_59": 11677,
    "w1_60_69": 6415,
    "w1_70plus": 7160,
    "population": 73923,
    "atLeastOneDose": 37602,
    "fullyVaccinated": 36907
  },
  "1661": {
    "teryt": "1661",
    "w1_12_19": 5021,
    "w1_20_39": 20831,
    "w1_40_59": 24451,
    "w1_60_69": 13148,
    "w1_70plus": 17338,
    "population": 127839,
    "atLeastOneDose": 82777,
    "fullyVaccinated": 81062
  },
  "1801": {
    "teryt": "1801",
    "w1_12_19": 471,
    "w1_20_39": 2105,
    "w1_40_59": 2829,
    "w1_60_69": 1879,
    "w1_70plus": 1761,
    "population": 21489,
    "atLeastOneDose": 9134,
    "fullyVaccinated": 8878
  },
  "1802": {
    "teryt": "1802",
    "w1_12_19": 923,
    "w1_20_39": 6231,
    "w1_40_59": 7971,
    "w1_60_69": 4681,
    "w1_70plus": 4848,
    "population": 65373,
    "atLeastOneDose": 24787,
    "fullyVaccinated": 24248
  },
  "1803": {
    "teryt": "1803",
    "w1_12_19": 2664,
    "w1_20_39": 14353,
    "w1_40_59": 18281,
    "w1_60_69": 10406,
    "w1_70plus": 10506,
    "population": 134991,
    "atLeastOneDose": 56649,
    "fullyVaccinated": 55381
  },
  "1804": {
    "teryt": "1804",
    "w1_12_19": 2420,
    "w1_20_39": 13611,
    "w1_40_59": 17451,
    "w1_60_69": 10258,
    "w1_70plus": 10301,
    "population": 119727,
    "atLeastOneDose": 54502,
    "fullyVaccinated": 53130
  },
  "1805": {
    "teryt": "1805",
    "w1_12_19": 1893,
    "w1_20_39": 11506,
    "w1_40_59": 15872,
    "w1_60_69": 8966,
    "w1_70plus": 9341,
    "population": 112863,
    "atLeastOneDose": 47863,
    "fullyVaccinated": 47078
  },
  "1806": {
    "teryt": "1806",
    "w1_12_19": 654,
    "w1_20_39": 5276,
    "w1_40_59": 6298,
    "w1_60_69": 3528,
    "w1_70plus": 3882,
    "population": 62039,
    "atLeastOneDose": 19741,
    "fullyVaccinated": 19271
  },
  "1807": {
    "teryt": "1807",
    "w1_12_19": 1678,
    "w1_20_39": 10788,
    "w1_40_59": 14532,
    "w1_60_69": 8398,
    "w1_70plus": 8890,
    "population": 111905,
    "atLeastOneDose": 44511,
    "fullyVaccinated": 43604
  },
  "1808": {
    "teryt": "1808",
    "w1_12_19": 1109,
    "w1_20_39": 6954,
    "w1_40_59": 8551,
    "w1_60_69": 5185,
    "w1_70plus": 5314,
    "population": 68996,
    "atLeastOneDose": 27267,
    "fullyVaccinated": 26697
  },
  "1809": {
    "teryt": "1809",
    "w1_12_19": 1296,
    "w1_20_39": 6327,
    "w1_40_59": 8352,
    "w1_60_69": 4979,
    "w1_70plus": 5179,
    "population": 54711,
    "atLeastOneDose": 26327,
    "fullyVaccinated": 25586
  },
  "1810": {
    "teryt": "1810",
    "w1_12_19": 1736,
    "w1_20_39": 9412,
    "w1_40_59": 11638,
    "w1_60_69": 6247,
    "w1_70plus": 7058,
    "population": 81226,
    "atLeastOneDose": 36468,
    "fullyVaccinated": 35794
  },
  "1811": {
    "teryt": "1811",
    "w1_12_19": 2852,
    "w1_20_39": 15434,
    "w1_40_59": 19743,
    "w1_60_69": 11179,
    "w1_70plus": 12156,
    "population": 136441,
    "atLeastOneDose": 61800,
    "fullyVaccinated": 59995
  },
  "1812": {
    "teryt": "1812",
    "w1_12_19": 1028,
    "w1_20_39": 6176,
    "w1_40_59": 7601,
    "w1_60_69": 4579,
    "w1_70plus": 4716,
    "population": 66221,
    "atLeastOneDose": 24193,
    "fullyVaccinated": 23604
  },
  "1813": {
    "teryt": "1813",
    "w1_12_19": 1683,
    "w1_20_39": 8567,
    "w1_40_59": 10954,
    "w1_60_69": 5880,
    "w1_70plus": 5426,
    "population": 73919,
    "atLeastOneDose": 32804,
    "fullyVaccinated": 32018
  },
  "1814": {
    "teryt": "1814",
    "w1_12_19": 1538,
    "w1_20_39": 8614,
    "w1_40_59": 11057,
    "w1_60_69": 6294,
    "w1_70plus": 6481,
    "population": 77979,
    "atLeastOneDose": 34185,
    "fullyVaccinated": 33466
  },
  "1815": {
    "teryt": "1815",
    "w1_12_19": 1139,
    "w1_20_39": 7153,
    "w1_40_59": 8881,
    "w1_60_69": 4556,
    "w1_70plus": 4969,
    "population": 74573,
    "atLeastOneDose": 26881,
    "fullyVaccinated": 26346
  },
  "1816": {
    "teryt": "1816",
    "w1_12_19": 3897,
    "w1_20_39": 19178,
    "w1_40_59": 24627,
    "w1_60_69": 11764,
    "w1_70plus": 12818,
    "population": 170550,
    "atLeastOneDose": 73060,
    "fullyVaccinated": 71587
  },
  "1817": {
    "teryt": "1817",
    "w1_12_19": 1701,
    "w1_20_39": 8776,
    "w1_40_59": 12130,
    "w1_60_69": 7886,
    "w1_70plus": 8506,
    "population": 93818,
    "atLeastOneDose": 39313,
    "fullyVaccinated": 38448
  },
  "1818": {
    "teryt": "1818",
    "w1_12_19": 2026,
    "w1_20_39": 9854,
    "w1_40_59": 13483,
    "w1_60_69": 9100,
    "w1_70plus": 10230,
    "population": 105431,
    "atLeastOneDose": 45024,
    "fullyVaccinated": 43919
  },
  "1819": {
    "teryt": "1819",
    "w1_12_19": 1045,
    "w1_20_39": 5913,
    "w1_40_59": 7579,
    "w1_60_69": 4152,
    "w1_70plus": 4495,
    "population": 61161,
    "atLeastOneDose": 23346,
    "fullyVaccinated": 22912
  },
  "1820": {
    "teryt": "1820",
    "w1_12_19": 1000,
    "w1_20_39": 5470,
    "w1_40_59": 7297,
    "w1_60_69": 4259,
    "w1_70plus": 4483,
    "population": 52720,
    "atLeastOneDose": 22635,
    "fullyVaccinated": 22199
  },
  "1821": {
    "teryt": "1821",
    "w1_12_19": 466,
    "w1_20_39": 2445,
    "w1_40_59": 3549,
    "w1_60_69": 2179,
    "w1_70plus": 2291,
    "population": 26375,
    "atLeastOneDose": 11012,
    "fullyVaccinated": 10707
  },
  "1861": {
    "teryt": "1861",
    "w1_12_19": 1009,
    "w1_20_39": 4898,
    "w1_40_59": 6690,
    "w1_60_69": 4537,
    "w1_70plus": 5388,
    "population": 45944,
    "atLeastOneDose": 22758,
    "fullyVaccinated": 22248
  },
  "1862": {
    "teryt": "1862",
    "w1_12_19": 1735,
    "w1_20_39": 7078,
    "w1_40_59": 9983,
    "w1_60_69": 6503,
    "w1_70plus": 7054,
    "population": 59779,
    "atLeastOneDose": 32745,
    "fullyVaccinated": 32081
  },
  "1863": {
    "teryt": "1863",
    "w1_12_19": 6056,
    "w1_20_39": 31030,
    "w1_40_59": 32071,
    "w1_60_69": 17677,
    "w1_70plus": 20264,
    "population": 196638,
    "atLeastOneDose": 109212,
    "fullyVaccinated": 106993
  },
  "1864": {
    "teryt": "1864",
    "w1_12_19": 1412,
    "w1_20_39": 5660,
    "w1_40_59": 8316,
    "w1_60_69": 5024,
    "w1_70plus": 6066,
    "population": 46360,
    "atLeastOneDose": 26733,
    "fullyVaccinated": 26214
  },
  "2001": {
    "teryt": "2001",
    "w1_12_19": 1536,
    "w1_20_39": 6332,
    "w1_40_59": 8183,
    "w1_60_69": 4945,
    "w1_70plus": 5543,
    "population": 57651,
    "atLeastOneDose": 26828,
    "fullyVaccinated": 26276
  },
  "2002": {
    "teryt": "2002",
    "w1_12_19": 4160,
    "w1_20_39": 17955,
    "w1_40_59": 24470,
    "w1_60_69": 13319,
    "w1_70plus": 13414,
    "population": 150845,
    "atLeastOneDose": 74333,
    "fullyVaccinated": 72557
  },
  "2003": {
    "teryt": "2003",
    "w1_12_19": 1032,
    "w1_20_39": 5329,
    "w1_40_59": 7198,
    "w1_60_69": 4866,
    "w1_70plus": 6137,
    "population": 53695,
    "atLeastOneDose": 24736,
    "fullyVaccinated": 24202
  },
  "2004": {
    "teryt": "2004",
    "w1_12_19": 929,
    "w1_20_39": 4306,
    "w1_40_59": 5721,
    "w1_60_69": 3778,
    "w1_70plus": 3680,
    "population": 46792,
    "atLeastOneDose": 18513,
    "fullyVaccinated": 17948
  },
  "2005": {
    "teryt": "2005",
    "w1_12_19": 704,
    "w1_20_39": 3647,
    "w1_40_59": 5453,
    "w1_60_69": 4272,
    "w1_70plus": 5271,
    "population": 41991,
    "atLeastOneDose": 19470,
    "fullyVaccinated": 19041
  },
  "2006": {
    "teryt": "2006",
    "w1_12_19": 616,
    "w1_20_39": 3756,
    "w1_40_59": 4692,
    "w1_60_69": 2732,
    "w1_70plus": 2899,
    "population": 37887,
    "atLeastOneDose": 14766,
    "fullyVaccinated": 14407
  },
  "2007": {
    "teryt": "2007",
    "w1_12_19": 1082,
    "w1_20_39": 5342,
    "w1_40_59": 6766,
    "w1_60_69": 3526,
    "w1_70plus": 3678,
    "population": 50819,
    "atLeastOneDose": 20575,
    "fullyVaccinated": 20118
  },
  "2008": {
    "teryt": "2008",
    "w1_12_19": 843,
    "w1_20_39": 3873,
    "w1_40_59": 4823,
    "w1_60_69": 3186,
    "w1_70plus": 3561,
    "population": 40070,
    "atLeastOneDose": 16420,
    "fullyVaccinated": 15974
  },
  "2009": {
    "teryt": "2009",
    "w1_12_19": 491,
    "w1_20_39": 2247,
    "w1_40_59": 2939,
    "w1_60_69": 1781,
    "w1_70plus": 1987,
    "population": 19689,
    "atLeastOneDose": 9529,
    "fullyVaccinated": 9336
  },
  "2010": {
    "teryt": "2010",
    "w1_12_19": 675,
    "w1_20_39": 3855,
    "w1_40_59": 5076,
    "w1_60_69": 3769,
    "w1_70plus": 4667,
    "population": 43618,
    "atLeastOneDose": 18151,
    "fullyVaccinated": 17730
  },
  "2011": {
    "teryt": "2011",
    "w1_12_19": 1775,
    "w1_20_39": 7477,
    "w1_40_59": 10090,
    "w1_60_69": 6286,
    "w1_70plus": 6964,
    "population": 65883,
    "atLeastOneDose": 32945,
    "fullyVaccinated": 32297
  },
  "2012": {
    "teryt": "2012",
    "w1_12_19": 975,
    "w1_20_39": 3889,
    "w1_40_59": 5037,
    "w1_60_69": 2834,
    "w1_70plus": 2799,
    "population": 35577,
    "atLeastOneDose": 15663,
    "fullyVaccinated": 15318
  },
  "2013": {
    "teryt": "2013",
    "w1_12_19": 1415,
    "w1_20_39": 6458,
    "w1_40_59": 8024,
    "w1_60_69": 5005,
    "w1_70plus": 5749,
    "population": 56408,
    "atLeastOneDose": 26893,
    "fullyVaccinated": 26274
  },
  "2014": {
    "teryt": "2014",
    "w1_12_19": 1031,
    "w1_20_39": 5322,
    "w1_40_59": 6229,
    "w1_60_69": 3844,
    "w1_70plus": 3878,
    "population": 43191,
    "atLeastOneDose": 20483,
    "fullyVaccinated": 20015
  },
  "2061": {
    "teryt": "2061",
    "w1_12_19": 9554,
    "w1_20_39": 44093,
    "w1_40_59": 52292,
    "w1_60_69": 28344,
    "w1_70plus": 32481,
    "population": 296958,
    "atLeastOneDose": 169751,
    "fullyVaccinated": 166078
  },
  "2062": {
    "teryt": "2062",
    "w1_12_19": 1695,
    "w1_20_39": 7416,
    "w1_40_59": 9507,
    "w1_60_69": 6469,
    "w1_70plus": 5932,
    "population": 62573,
    "atLeastOneDose": 31360,
    "fullyVaccinated": 30739
  },
  "2063": {
    "teryt": "2063",
    "w1_12_19": 1967,
    "w1_20_39": 9094,
    "w1_40_59": 11404,
    "w1_60_69": 6827,
    "w1_70plus": 6008,
    "population": 69639,
    "atLeastOneDose": 35681,
    "fullyVaccinated": 34877
  },
  "2201": {
    "teryt": "2201",
    "w1_12_19": 2935,
    "w1_20_39": 11143,
    "w1_40_59": 12907,
    "w1_60_69": 7672,
    "w1_70plus": 6890,
    "population": 79114,
    "atLeastOneDose": 42358,
    "fullyVaccinated": 41427
  },
  "2202": {
    "teryt": "2202",
    "w1_12_19": 3812,
    "w1_20_39": 13930,
    "w1_40_59": 17079,
    "w1_60_69": 9446,
    "w1_70plus": 9237,
    "population": 97661,
    "atLeastOneDose": 54485,
    "fullyVaccinated": 53498
  },
  "2203": {
    "teryt": "2203",
    "w1_12_19": 2230,
    "w1_20_39": 7539,
    "w1_40_59": 9663,
    "w1_60_69": 6239,
    "w1_70plus": 5482,
    "population": 55835,
    "atLeastOneDose": 31626,
    "fullyVaccinated": 30983
  },
  "2204": {
    "teryt": "2204",
    "w1_12_19": 6571,
    "w1_20_39": 22904,
    "w1_40_59": 26228,
    "w1_60_69": 10312,
    "w1_70plus": 9343,
    "population": 120327,
    "atLeastOneDose": 78051,
    "fullyVaccinated": 76226
  },
  "2205": {
    "teryt": "2205",
    "w1_12_19": 6483,
    "w1_20_39": 22526,
    "w1_40_59": 24822,
    "w1_60_69": 10383,
    "w1_70plus": 9144,
    "population": 141892,
    "atLeastOneDose": 75430,
    "fullyVaccinated": 73780
  },
  "2206": {
    "teryt": "2206",
    "w1_12_19": 3263,
    "w1_20_39": 11063,
    "w1_40_59": 12998,
    "w1_60_69": 6667,
    "w1_70plus": 6203,
    "population": 72923,
    "atLeastOneDose": 41099,
    "fullyVaccinated": 40222
  },
  "2207": {
    "teryt": "2207",
    "w1_12_19": 3200,
    "w1_20_39": 10658,
    "w1_40_59": 13986,
    "w1_60_69": 8105,
    "w1_70plus": 7127,
    "population": 82963,
    "atLeastOneDose": 44001,
    "fullyVaccinated": 42834
  },
  "2208": {
    "teryt": "2208",
    "w1_12_19": 2603,
    "w1_20_39": 9259,
    "w1_40_59": 11296,
    "w1_60_69": 6895,
    "w1_70plus": 6408,
    "population": 66083,
    "atLeastOneDose": 37191,
    "fullyVaccinated": 36523
  },
  "2209": {
    "teryt": "2209",
    "w1_12_19": 2965,
    "w1_20_39": 9264,
    "w1_40_59": 11896,
    "w1_60_69": 7134,
    "w1_70plus": 6587,
    "population": 63204,
    "atLeastOneDose": 38787,
    "fullyVaccinated": 37890
  },
  "2210": {
    "teryt": "2210",
    "w1_12_19": 1568,
    "w1_20_39": 5169,
    "w1_40_59": 6490,
    "w1_60_69": 3847,
    "w1_70plus": 3307,
    "population": 35438,
    "atLeastOneDose": 20861,
    "fullyVaccinated": 20363
  },
  "2211": {
    "teryt": "2211",
    "w1_12_19": 4382,
    "w1_20_39": 15032,
    "w1_40_59": 17919,
    "w1_60_69": 8117,
    "w1_70plus": 7340,
    "population": 87568,
    "atLeastOneDose": 53985,
    "fullyVaccinated": 52679
  },
  "2212": {
    "teryt": "2212",
    "w1_12_19": 3684,
    "w1_20_39": 13847,
    "w1_40_59": 17888,
    "w1_60_69": 10330,
    "w1_70plus": 8580,
    "population": 98832,
    "atLeastOneDose": 55359,
    "fullyVaccinated": 54068
  },
  "2213": {
    "teryt": "2213",
    "w1_12_19": 5329,
    "w1_20_39": 18287,
    "w1_40_59": 21877,
    "w1_60_69": 11717,
    "w1_70plus": 11138,
    "population": 128210,
    "atLeastOneDose": 69834,
    "fullyVaccinated": 68196
  },
  "2214": {
    "teryt": "2214",
    "w1_12_19": 5386,
    "w1_20_39": 18200,
    "w1_40_59": 21930,
    "w1_60_69": 11366,
    "w1_70plus": 11183,
    "population": 115220,
    "atLeastOneDose": 69794,
    "fullyVaccinated": 68408
  },
  "2215": {
    "teryt": "2215",
    "w1_12_19": 9864,
    "w1_20_39": 35236,
    "w1_40_59": 41363,
    "w1_60_69": 19079,
    "w1_70plus": 17549,
    "population": 219457,
    "atLeastOneDose": 126508,
    "fullyVaccinated": 123503
  },
  "2216": {
    "teryt": "2216",
    "w1_12_19": 1862,
    "w1_20_39": 6056,
    "w1_40_59": 7218,
    "w1_60_69": 4506,
    "w1_70plus": 3781,
    "population": 41104,
    "atLeastOneDose": 23982,
    "fullyVaccinated": 23557
  },
  "2261": {
    "teryt": "2261",
    "w1_12_19": 22513,
    "w1_20_39": 102204,
    "w1_40_59": 97840,
    "w1_60_69": 46655,
    "w1_70plus": 64762,
    "population": 470805,
    "atLeastOneDose": 345231,
    "fullyVaccinated": 337129
  },
  "2262": {
    "teryt": "2262",
    "w1_12_19": 11071,
    "w1_20_39": 43857,
    "w1_40_59": 49897,
    "w1_60_69": 25874,
    "w1_70plus": 36449,
    "population": 244969,
    "atLeastOneDose": 172118,
    "fullyVaccinated": 167791
  },
  "2263": {
    "teryt": "2263",
    "w1_12_19": 3525,
    "w1_20_39": 13220,
    "w1_40_59": 16869,
    "w1_60_69": 10658,
    "w1_70plus": 12555,
    "population": 89780,
    "atLeastOneDose": 57970,
    "fullyVaccinated": 56832
  },
  "2264": {
    "teryt": "2264",
    "w1_12_19": 1333,
    "w1_20_39": 5748,
    "w1_40_59": 6507,
    "w1_60_69": 3767,
    "w1_70plus": 6312,
    "population": 35286,
    "atLeastOneDose": 24339,
    "fullyVaccinated": 23714
  },
  "2401": {
    "teryt": "2401",
    "w1_12_19": 5952,
    "w1_20_39": 20202,
    "w1_40_59": 31049,
    "w1_60_69": 17606,
    "w1_70plus": 19268,
    "population": 147259,
    "atLeastOneDose": 96159,
    "fullyVaccinated": 94110
  },
  "2402": {
    "teryt": "2402",
    "w1_12_19": 6911,
    "w1_20_39": 24582,
    "w1_40_59": 32636,
    "w1_60_69": 16551,
    "w1_70plus": 16881,
    "population": 166348,
    "atLeastOneDose": 99556,
    "fullyVaccinated": 97764
  },
  "2403": {
    "teryt": "2403",
    "w1_12_19": 5644,
    "w1_20_39": 22954,
    "w1_40_59": 31002,
    "w1_60_69": 16738,
    "w1_70plus": 18325,
    "population": 177536,
    "atLeastOneDose": 96142,
    "fullyVaccinated": 94267
  },
  "2404": {
    "teryt": "2404",
    "w1_12_19": 4168,
    "w1_20_39": 17371,
    "w1_40_59": 25443,
    "w1_60_69": 14104,
    "w1_70plus": 13838,
    "population": 134106,
    "atLeastOneDose": 75838,
    "fullyVaccinated": 74344
  },
  "2405": {
    "teryt": "2405",
    "w1_12_19": 4681,
    "w1_20_39": 15722,
    "w1_40_59": 21698,
    "w1_60_69": 11252,
    "w1_70plus": 11636,
    "population": 115416,
    "atLeastOneDose": 66512,
    "fullyVaccinated": 65200
  },
  "2406": {
    "teryt": "2406",
    "w1_12_19": 2325,
    "w1_20_39": 11337,
    "w1_40_59": 15612,
    "w1_60_69": 8316,
    "w1_70plus": 8769,
    "population": 84330,
    "atLeastOneDose": 46833,
    "fullyVaccinated": 45660
  },
  "2407": {
    "teryt": "2407",
    "w1_12_19": 2365,
    "w1_20_39": 9578,
    "w1_40_59": 12527,
    "w1_60_69": 6647,
    "w1_70plus": 7158,
    "population": 76109,
    "atLeastOneDose": 38815,
    "fullyVaccinated": 37998
  },
  "2408": {
    "teryt": "2408",
    "w1_12_19": 4458,
    "w1_20_39": 14965,
    "w1_40_59": 19931,
    "w1_60_69": 9635,
    "w1_70plus": 9808,
    "population": 99202,
    "atLeastOneDose": 60433,
    "fullyVaccinated": 59288
  },
  "2409": {
    "teryt": "2409",
    "w1_12_19": 1949,
    "w1_20_39": 8627,
    "w1_40_59": 12847,
    "w1_60_69": 7558,
    "w1_70plus": 7867,
    "population": 70486,
    "atLeastOneDose": 39371,
    "fullyVaccinated": 38608
  },
  "2410": {
    "teryt": "2410",
    "w1_12_19": 4391,
    "w1_20_39": 16896,
    "w1_40_59": 20684,
    "w1_60_69": 10878,
    "w1_70plus": 9312,
    "population": 111814,
    "atLeastOneDose": 63228,
    "fullyVaccinated": 62028
  },
  "2411": {
    "teryt": "2411",
    "w1_12_19": 2972,
    "w1_20_39": 12929,
    "w1_40_59": 16826,
    "w1_60_69": 9825,
    "w1_70plus": 10542,
    "population": 107410,
    "atLeastOneDose": 53753,
    "fullyVaccinated": 52845
  },
  "2412": {
    "teryt": "2412",
    "w1_12_19": 2913,
    "w1_20_39": 10646,
    "w1_40_59": 14122,
    "w1_60_69": 7550,
    "w1_70plus": 7133,
    "population": 78166,
    "atLeastOneDose": 43184,
    "fullyVaccinated": 42567
  },
  "2413": {
    "teryt": "2413",
    "w1_12_19": 5571,
    "w1_20_39": 20093,
    "w1_40_59": 26884,
    "w1_60_69": 13887,
    "w1_70plus": 15732,
    "population": 140780,
    "atLeastOneDose": 84134,
    "fullyVaccinated": 82715
  },
  "2414": {
    "teryt": "2414",
    "w1_12_19": 2390,
    "w1_20_39": 9259,
    "w1_40_59": 11510,
    "w1_60_69": 6090,
    "w1_70plus": 5197,
    "population": 59823,
    "atLeastOneDose": 35258,
    "fullyVaccinated": 34632
  },
  "2415": {
    "teryt": "2415",
    "w1_12_19": 5029,
    "w1_20_39": 19333,
    "w1_40_59": 27009,
    "w1_60_69": 14179,
    "w1_70plus": 16256,
    "population": 156579,
    "atLeastOneDose": 83037,
    "fullyVaccinated": 81646
  },
  "2416": {
    "teryt": "2416",
    "w1_12_19": 3770,
    "w1_20_39": 14878,
    "w1_40_59": 22615,
    "w1_60_69": 13308,
    "w1_70plus": 14949,
    "population": 116672,
    "atLeastOneDose": 70434,
    "fullyVaccinated": 69038
  },
  "2417": {
    "teryt": "2417",
    "w1_12_19": 5084,
    "w1_20_39": 21285,
    "w1_40_59": 27473,
    "w1_60_69": 14145,
    "w1_70plus": 14281,
    "population": 152199,
    "atLeastOneDose": 83321,
    "fullyVaccinated": 81494
  },
  "2461": {
    "teryt": "2461",
    "w1_12_19": 6373,
    "w1_20_39": 25339,
    "w1_40_59": 32261,
    "w1_60_69": 17916,
    "w1_70plus": 23117,
    "population": 169756,
    "atLeastOneDose": 107134,
    "fullyVaccinated": 105095
  },
  "2462": {
    "teryt": "2462",
    "w1_12_19": 5973,
    "w1_20_39": 21729,
    "w1_40_59": 28756,
    "w1_60_69": 16003,
    "w1_70plus": 19037,
    "population": 163255,
    "atLeastOneDose": 93483,
    "fullyVaccinated": 91578
  },
  "2463": {
    "teryt": "2463",
    "w1_12_19": 4202,
    "w1_20_39": 15558,
    "w1_40_59": 20686,
    "w1_60_69": 9690,
    "w1_70plus": 13256,
    "population": 106846,
    "atLeastOneDose": 65005,
    "fullyVaccinated": 63564
  },
  "2464": {
    "teryt": "2464",
    "w1_12_19": 6986,
    "w1_20_39": 29206,
    "w1_40_59": 42238,
    "w1_60_69": 26136,
    "w1_70plus": 30343,
    "population": 217530,
    "atLeastOneDose": 136904,
    "fullyVaccinated": 134068
  },
  "2465": {
    "teryt": "2465",
    "w1_12_19": 4585,
    "w1_20_39": 15683,
    "w1_40_59": 23980,
    "w1_60_69": 15612,
    "w1_70plus": 15228,
    "population": 118285,
    "atLeastOneDose": 76533,
    "fullyVaccinated": 74940
  },
  "2466": {
    "teryt": "2466",
    "w1_12_19": 6767,
    "w1_20_39": 26899,
    "w1_40_59": 33646,
    "w1_60_69": 19347,
    "w1_70plus": 23319,
    "population": 177049,
    "atLeastOneDose": 112683,
    "fullyVaccinated": 110445
  },
  "2467": {
    "teryt": "2467",
    "w1_12_19": 2798,
    "w1_20_39": 10329,
    "w1_40_59": 15389,
    "w1_60_69": 7317,
    "w1_70plus": 11259,
    "population": 88038,
    "atLeastOneDose": 47730,
    "fullyVaccinated": 46837
  },
  "2468": {
    "teryt": "2468",
    "w1_12_19": 3102,
    "w1_20_39": 12310,
    "w1_40_59": 17203,
    "w1_60_69": 10081,
    "w1_70plus": 10049,
    "population": 90368,
    "atLeastOneDose": 53783,
    "fullyVaccinated": 52777
  },
  "2469": {
    "teryt": "2469",
    "w1_12_19": 10915,
    "w1_20_39": 50392,
    "w1_40_59": 56743,
    "w1_60_69": 32913,
    "w1_70plus": 41447,
    "population": 290553,
    "atLeastOneDose": 197307,
    "fullyVaccinated": 193118
  },
  "2470": {
    "teryt": "2470",
    "w1_12_19": 3063,
    "w1_20_39": 11341,
    "w1_40_59": 14344,
    "w1_60_69": 8131,
    "w1_70plus": 7912,
    "population": 74559,
    "atLeastOneDose": 45879,
    "fullyVaccinated": 45033
  },
  "2471": {
    "teryt": "2471",
    "w1_12_19": 2051,
    "w1_20_39": 7936,
    "w1_40_59": 10248,
    "w1_60_69": 6470,
    "w1_70plus": 6536,
    "population": 54702,
    "atLeastOneDose": 33977,
    "fullyVaccinated": 33369
  },
  "2472": {
    "teryt": "2472",
    "w1_12_19": 5712,
    "w1_20_39": 20696,
    "w1_40_59": 26668,
    "w1_60_69": 15120,
    "w1_70plus": 15424,
    "population": 136423,
    "atLeastOneDose": 85612,
    "fullyVaccinated": 83911
  },
  "2473": {
    "teryt": "2473",
    "w1_12_19": 5050,
    "w1_20_39": 18344,
    "w1_40_59": 24555,
    "w1_60_69": 13867,
    "w1_70plus": 14489,
    "population": 137128,
    "atLeastOneDose": 77740,
    "fullyVaccinated": 76358
  },
  "2474": {
    "teryt": "2474",
    "w1_12_19": 2479,
    "w1_20_39": 9233,
    "w1_40_59": 12565,
    "w1_60_69": 7662,
    "w1_70plus": 8446,
    "population": 66270,
    "atLeastOneDose": 41258,
    "fullyVaccinated": 40551
  },
  "2475": {
    "teryt": "2475",
    "w1_12_19": 7104,
    "w1_20_39": 27166,
    "w1_40_59": 38843,
    "w1_60_69": 25220,
    "w1_70plus": 28652,
    "population": 197586,
    "atLeastOneDose": 129479,
    "fullyVaccinated": 126998
  },
  "2476": {
    "teryt": "2476",
    "w1_12_19": 1693,
    "w1_20_39": 6357,
    "w1_40_59": 8472,
    "w1_60_69": 4876,
    "w1_70plus": 5504,
    "population": 49108,
    "atLeastOneDose": 27511,
    "fullyVaccinated": 26885
  },
  "2477": {
    "teryt": "2477",
    "w1_12_19": 5332,
    "w1_20_39": 19232,
    "w1_40_59": 24220,
    "w1_60_69": 15856,
    "w1_70plus": 15068,
    "population": 126871,
    "atLeastOneDose": 81741,
    "fullyVaccinated": 79939
  },
  "2478": {
    "teryt": "2478",
    "w1_12_19": 6019,
    "w1_20_39": 22559,
    "w1_40_59": 29312,
    "w1_60_69": 16237,
    "w1_70plus": 17031,
    "population": 170924,
    "atLeastOneDose": 93280,
    "fullyVaccinated": 91401
  },
  "2479": {
    "teryt": "2479",
    "w1_12_19": 2375,
    "w1_20_39": 7999,
    "w1_40_59": 11091,
    "w1_60_69": 6747,
    "w1_70plus": 6486,
    "population": 62844,
    "atLeastOneDose": 35366,
    "fullyVaccinated": 34701
  },
  "2601": {
    "teryt": "2601",
    "w1_12_19": 2051,
    "w1_20_39": 9360,
    "w1_40_59": 12812,
    "w1_60_69": 7446,
    "w1_70plus": 8492,
    "population": 71125,
    "atLeastOneDose": 40593,
    "fullyVaccinated": 39672
  },
  "2602": {
    "teryt": "2602",
    "w1_12_19": 2996,
    "w1_20_39": 12244,
    "w1_40_59": 15940,
    "w1_60_69": 9516,
    "w1_70plus": 10043,
    "population": 84908,
    "atLeastOneDose": 51432,
    "fullyVaccinated": 50539
  },
  "2603": {
    "teryt": "2603",
    "w1_12_19": 1001,
    "w1_20_39": 4185,
    "w1_40_59": 5425,
    "w1_60_69": 3274,
    "w1_70plus": 3696,
    "population": 33340,
    "atLeastOneDose": 17789,
    "fullyVaccinated": 17375
  },
  "2604": {
    "teryt": "2604",
    "w1_12_19": 5967,
    "w1_20_39": 28698,
    "w1_40_59": 36636,
    "w1_60_69": 18800,
    "w1_70plus": 16742,
    "population": 210992,
    "atLeastOneDose": 107969,
    "fullyVaccinated": 105530
  },
  "2605": {
    "teryt": "2605",
    "w1_12_19": 2333,
    "w1_20_39": 9973,
    "w1_40_59": 13599,
    "w1_60_69": 8411,
    "w1_70plus": 9387,
    "population": 79072,
    "atLeastOneDose": 44200,
    "fullyVaccinated": 43347
  },
  "2606": {
    "teryt": "2606",
    "w1_12_19": 1301,
    "w1_20_39": 6045,
    "w1_40_59": 8249,
    "w1_60_69": 5315,
    "w1_70plus": 5418,
    "population": 51525,
    "atLeastOneDose": 26508,
    "fullyVaccinated": 25969
  },
  "2607": {
    "teryt": "2607",
    "w1_12_19": 2811,
    "w1_20_39": 11660,
    "w1_40_59": 17495,
    "w1_60_69": 12734,
    "w1_70plus": 13777,
    "population": 107711,
    "atLeastOneDose": 59004,
    "fullyVaccinated": 57870
  },
  "2608": {
    "teryt": "2608",
    "w1_12_19": 1068,
    "w1_20_39": 5302,
    "w1_40_59": 6939,
    "w1_60_69": 4324,
    "w1_70plus": 4859,
    "population": 38487,
    "atLeastOneDose": 22675,
    "fullyVaccinated": 22134
  },
  "2609": {
    "teryt": "2609",
    "w1_12_19": 2212,
    "w1_20_39": 9966,
    "w1_40_59": 13550,
    "w1_60_69": 7795,
    "w1_70plus": 9280,
    "population": 76346,
    "atLeastOneDose": 43201,
    "fullyVaccinated": 42267
  },
  "2610": {
    "teryt": "2610",
    "w1_12_19": 1987,
    "w1_20_39": 8712,
    "w1_40_59": 12258,
    "w1_60_69": 8627,
    "w1_70plus": 9616,
    "population": 73163,
    "atLeastOneDose": 41624,
    "fullyVaccinated": 40740
  },
  "2611": {
    "teryt": "2611",
    "w1_12_19": 2431,
    "w1_20_39": 10510,
    "w1_40_59": 14320,
    "w1_60_69": 9494,
    "w1_70plus": 10874,
    "population": 88549,
    "atLeastOneDose": 48092,
    "fullyVaccinated": 47043
  },
  "2612": {
    "teryt": "2612",
    "w1_12_19": 1986,
    "w1_20_39": 9590,
    "w1_40_59": 12420,
    "w1_60_69": 7605,
    "w1_70plus": 7451,
    "population": 71250,
    "atLeastOneDose": 39362,
    "fullyVaccinated": 38539
  },
  "2613": {
    "teryt": "2613",
    "w1_12_19": 1399,
    "w1_20_39": 6190,
    "w1_40_59": 7938,
    "w1_60_69": 4631,
    "w1_70plus": 5031,
    "population": 44743,
    "atLeastOneDose": 25435,
    "fullyVaccinated": 25001
  },
  "2661": {
    "teryt": "2661",
    "w1_12_19": 7303,
    "w1_20_39": 27005,
    "w1_40_59": 36077,
    "w1_60_69": 21314,
    "w1_70plus": 27439,
    "population": 193415,
    "atLeastOneDose": 121470,
    "fullyVaccinated": 118760
  },
  "2801": {
    "teryt": "2801",
    "w1_12_19": 2398,
    "w1_20_39": 7856,
    "w1_40_59": 10323,
    "w1_60_69": 6487,
    "w1_70plus": 5871,
    "population": 56562,
    "atLeastOneDose": 33539,
    "fullyVaccinated": 32856
  },
  "2802": {
    "teryt": "2802",
    "w1_12_19": 1541,
    "w1_20_39": 5912,
    "w1_40_59": 7150,
    "w1_60_69": 4411,
    "w1_70plus": 3827,
    "population": 40776,
    "atLeastOneDose": 23232,
    "fullyVaccinated": 22792
  },
  "2803": {
    "teryt": "2803",
    "w1_12_19": 2729,
    "w1_20_39": 9444,
    "w1_40_59": 12282,
    "w1_60_69": 6982,
    "w1_70plus": 6158,
    "population": 64768,
    "atLeastOneDose": 38224,
    "fullyVaccinated": 37484
  },
  "2804": {
    "teryt": "2804",
    "w1_12_19": 2561,
    "w1_20_39": 8061,
    "w1_40_59": 10178,
    "w1_60_69": 6171,
    "w1_70plus": 4977,
    "population": 56986,
    "atLeastOneDose": 32695,
    "fullyVaccinated": 31987
  },
  "2805": {
    "teryt": "2805",
    "w1_12_19": 2584,
    "w1_20_39": 10422,
    "w1_40_59": 13259,
    "w1_60_69": 8078,
    "w1_70plus": 7378,
    "population": 91395,
    "atLeastOneDose": 42309,
    "fullyVaccinated": 41216
  },
  "2806": {
    "teryt": "2806",
    "w1_12_19": 2257,
    "w1_20_39": 7672,
    "w1_40_59": 10071,
    "w1_60_69": 6231,
    "w1_70plus": 6000,
    "population": 56227,
    "atLeastOneDose": 32814,
    "fullyVaccinated": 32165
  },
  "2807": {
    "teryt": "2807",
    "w1_12_19": 4012,
    "w1_20_39": 13204,
    "w1_40_59": 16547,
    "w1_60_69": 9744,
    "w1_70plus": 8803,
    "population": 92644,
    "atLeastOneDose": 53358,
    "fullyVaccinated": 52241
  },
  "2808": {
    "teryt": "2808",
    "w1_12_19": 2239,
    "w1_20_39": 7445,
    "w1_40_59": 10316,
    "w1_60_69": 7009,
    "w1_70plus": 6671,
    "population": 61772,
    "atLeastOneDose": 34182,
    "fullyVaccinated": 33472
  },
  "2809": {
    "teryt": "2809",
    "w1_12_19": 1500,
    "w1_20_39": 5220,
    "w1_40_59": 6908,
    "w1_60_69": 4280,
    "w1_70plus": 4209,
    "population": 40852,
    "atLeastOneDose": 22472,
    "fullyVaccinated": 22036
  },
  "2810": {
    "teryt": "2810",
    "w1_12_19": 1578,
    "w1_20_39": 6013,
    "w1_40_59": 8022,
    "w1_60_69": 5179,
    "w1_70plus": 4658,
    "population": 49439,
    "atLeastOneDose": 25783,
    "fullyVaccinated": 25124
  },
  "2811": {
    "teryt": "2811",
    "w1_12_19": 1212,
    "w1_20_39": 4122,
    "w1_40_59": 5673,
    "w1_60_69": 3280,
    "w1_70plus": 3074,
    "population": 32638,
    "atLeastOneDose": 17632,
    "fullyVaccinated": 17202
  },
  "2812": {
    "teryt": "2812",
    "w1_12_19": 1956,
    "w1_20_39": 6471,
    "w1_40_59": 7759,
    "w1_60_69": 4078,
    "w1_70plus": 3940,
    "population": 43721,
    "atLeastOneDose": 24800,
    "fullyVaccinated": 24312
  },
  "2813": {
    "teryt": "2813",
    "w1_12_19": 1170,
    "w1_20_39": 4219,
    "w1_40_59": 5188,
    "w1_60_69": 3328,
    "w1_70plus": 3005,
    "population": 33993,
    "atLeastOneDose": 17192,
    "fullyVaccinated": 16847
  },
  "2814": {
    "teryt": "2814",
    "w1_12_19": 5395,
    "w1_20_39": 17666,
    "w1_40_59": 24012,
    "w1_60_69": 13128,
    "w1_70plus": 10687,
    "population": 127544,
    "atLeastOneDose": 72502,
    "fullyVaccinated": 70858
  },
  "2815": {
    "teryt": "2815",
    "w1_12_19": 3722,
    "w1_20_39": 13341,
    "w1_40_59": 17965,
    "w1_60_69": 10972,
    "w1_70plus": 10103,
    "population": 103492,
    "atLeastOneDose": 56962,
    "fullyVaccinated": 55568
  },
  "2816": {
    "teryt": "2816",
    "w1_12_19": 1757,
    "w1_20_39": 6756,
    "w1_40_59": 8748,
    "w1_60_69": 5064,
    "w1_70plus": 5200,
    "population": 55833,
    "atLeastOneDose": 27829,
    "fullyVaccinated": 27059
  },
  "2817": {
    "teryt": "2817",
    "w1_12_19": 2435,
    "w1_20_39": 8683,
    "w1_40_59": 11699,
    "w1_60_69": 6960,
    "w1_70plus": 6412,
    "population": 69089,
    "atLeastOneDose": 36874,
    "fullyVaccinated": 35944
  },
  "2818": {
    "teryt": "2818",
    "w1_12_19": 1012,
    "w1_20_39": 3517,
    "w1_40_59": 4267,
    "w1_60_69": 2553,
    "w1_70plus": 2381,
    "population": 26489,
    "atLeastOneDose": 13946,
    "fullyVaccinated": 13659
  },
  "2819": {
    "teryt": "2819",
    "w1_12_19": 777,
    "w1_20_39": 3060,
    "w1_40_59": 4089,
    "w1_60_69": 2635,
    "w1_70plus": 2524,
    "population": 22444,
    "atLeastOneDose": 13327,
    "fullyVaccinated": 13100
  },
  "2861": {
    "teryt": "2861",
    "w1_12_19": 4820,
    "w1_20_39": 16307,
    "w1_40_59": 21695,
    "w1_60_69": 13890,
    "w1_70plus": 14910,
    "population": 118582,
    "atLeastOneDose": 73183,
    "fullyVaccinated": 71809
  },
  "2862": {
    "teryt": "2862",
    "w1_12_19": 7245,
    "w1_20_39": 27020,
    "w1_40_59": 33037,
    "w1_60_69": 18814,
    "w1_70plus": 21843,
    "population": 171249,
    "atLeastOneDose": 110788,
    "fullyVaccinated": 108312
  },
  "3001": {
    "teryt": "3001",
    "w1_12_19": 2325,
    "w1_20_39": 7226,
    "w1_40_59": 9360,
    "w1_60_69": 5097,
    "w1_70plus": 4876,
    "population": 46824,
    "atLeastOneDose": 29535,
    "fullyVaccinated": 28937
  },
  "3002": {
    "teryt": "3002",
    "w1_12_19": 3851,
    "w1_20_39": 12992,
    "w1_40_59": 16795,
    "w1_60_69": 8993,
    "w1_70plus": 8814,
    "population": 86590,
    "atLeastOneDose": 52561,
    "fullyVaccinated": 51189
  },
  "3003": {
    "teryt": "3003",
    "w1_12_19": 6518,
    "w1_20_39": 22599,
    "w1_40_59": 28424,
    "w1_60_69": 15107,
    "w1_70plus": 15033,
    "population": 145068,
    "atLeastOneDose": 89721,
    "fullyVaccinated": 87974
  },
  "3004": {
    "teryt": "3004",
    "w1_12_19": 2672,
    "w1_20_39": 10251,
    "w1_40_59": 12851,
    "w1_60_69": 7295,
    "w1_70plus": 7099,
    "population": 75732,
    "atLeastOneDose": 40931,
    "fullyVaccinated": 40223
  },
  "3005": {
    "teryt": "3005",
    "w1_12_19": 2506,
    "w1_20_39": 9464,
    "w1_40_59": 10356,
    "w1_60_69": 5161,
    "w1_70plus": 4404,
    "population": 51929,
    "atLeastOneDose": 32616,
    "fullyVaccinated": 31921
  },
  "3006": {
    "teryt": "3006",
    "w1_12_19": 2931,
    "w1_20_39": 11763,
    "w1_40_59": 13889,
    "w1_60_69": 7481,
    "w1_70plus": 7307,
    "population": 71425,
    "atLeastOneDose": 44328,
    "fullyVaccinated": 43577
  },
  "3007": {
    "teryt": "3007",
    "w1_12_19": 2261,
    "w1_20_39": 10608,
    "w1_40_59": 14340,
    "w1_60_69": 7182,
    "w1_70plus": 7446,
    "population": 82911,
    "atLeastOneDose": 42394,
    "fullyVaccinated": 41419
  },
  "3008": {
    "teryt": "3008",
    "w1_12_19": 2111,
    "w1_20_39": 9222,
    "w1_40_59": 10792,
    "w1_60_69": 5219,
    "w1_70plus": 5415,
    "population": 56298,
    "atLeastOneDose": 33287,
    "fullyVaccinated": 32672
  },
  "3009": {
    "teryt": "3009",
    "w1_12_19": 2499,
    "w1_20_39": 11014,
    "w1_40_59": 14866,
    "w1_60_69": 8477,
    "w1_70plus": 8677,
    "population": 86108,
    "atLeastOneDose": 45986,
    "fullyVaccinated": 45084
  },
  "3010": {
    "teryt": "3010",
    "w1_12_19": 5005,
    "w1_20_39": 20384,
    "w1_40_59": 25872,
    "w1_60_69": 12410,
    "w1_70plus": 11447,
    "population": 129904,
    "atLeastOneDose": 76163,
    "fullyVaccinated": 74706
  },
  "3011": {
    "teryt": "3011",
    "w1_12_19": 3604,
    "w1_20_39": 13186,
    "w1_40_59": 16019,
    "w1_60_69": 8461,
    "w1_70plus": 7883,
    "population": 78866,
    "atLeastOneDose": 50588,
    "fullyVaccinated": 49759
  },
  "3012": {
    "teryt": "3012",
    "w1_12_19": 2698,
    "w1_20_39": 10990,
    "w1_40_59": 13846,
    "w1_60_69": 7804,
    "w1_70plus": 7672,
    "population": 76998,
    "atLeastOneDose": 43810,
    "fullyVaccinated": 43101
  },
  "3013": {
    "teryt": "3013",
    "w1_12_19": 2292,
    "w1_20_39": 8443,
    "w1_40_59": 10662,
    "w1_60_69": 5098,
    "w1_70plus": 4790,
    "population": 57911,
    "atLeastOneDose": 31893,
    "fullyVaccinated": 31350
  },
  "3014": {
    "teryt": "3014",
    "w1_12_19": 1583,
    "w1_20_39": 6017,
    "w1_40_59": 7194,
    "w1_60_69": 4021,
    "w1_70plus": 3857,
    "population": 36633,
    "atLeastOneDose": 23169,
    "fullyVaccinated": 22742
  },
  "3015": {
    "teryt": "3015",
    "w1_12_19": 3471,
    "w1_20_39": 13150,
    "w1_40_59": 15221,
    "w1_60_69": 7518,
    "w1_70plus": 7170,
    "population": 75576,
    "atLeastOneDose": 47618,
    "fullyVaccinated": 46456
  },
  "3016": {
    "teryt": "3016",
    "w1_12_19": 3093,
    "w1_20_39": 9987,
    "w1_40_59": 12232,
    "w1_60_69": 6271,
    "w1_70plus": 5534,
    "population": 59821,
    "atLeastOneDose": 38274,
    "fullyVaccinated": 37425
  },
  "3017": {
    "teryt": "3017",
    "w1_12_19": 5106,
    "w1_20_39": 21544,
    "w1_40_59": 29364,
    "w1_60_69": 15952,
    "w1_70plus": 16840,
    "population": 161357,
    "atLeastOneDose": 90060,
    "fullyVaccinated": 88360
  },
  "3018": {
    "teryt": "3018",
    "w1_12_19": 1615,
    "w1_20_39": 7883,
    "w1_40_59": 9667,
    "w1_60_69": 4996,
    "w1_70plus": 5195,
    "population": 55265,
    "atLeastOneDose": 29647,
    "fullyVaccinated": 28932
  },
  "3019": {
    "teryt": "3019",
    "w1_12_19": 6172,
    "w1_20_39": 19818,
    "w1_40_59": 26522,
    "w1_60_69": 15062,
    "w1_70plus": 14337,
    "population": 135477,
    "atLeastOneDose": 83910,
    "fullyVaccinated": 82018
  },
  "3020": {
    "teryt": "3020",
    "w1_12_19": 2412,
    "w1_20_39": 9038,
    "w1_40_59": 12051,
    "w1_60_69": 6205,
    "w1_70plus": 6494,
    "population": 62763,
    "atLeastOneDose": 36810,
    "fullyVaccinated": 36237
  },
  "3021": {
    "teryt": "3021",
    "w1_12_19": 25330,
    "w1_20_39": 79652,
    "w1_40_59": 99113,
    "w1_60_69": 37991,
    "w1_70plus": 34500,
    "population": 406590,
    "atLeastOneDose": 288913,
    "fullyVaccinated": 282152
  },
  "3022": {
    "teryt": "3022",
    "w1_12_19": 2775,
    "w1_20_39": 9095,
    "w1_40_59": 11844,
    "w1_60_69": 6049,
    "w1_70plus": 6354,
    "population": 60188,
    "atLeastOneDose": 36853,
    "fullyVaccinated": 36312
  },
  "3023": {
    "teryt": "3023",
    "w1_12_19": 2537,
    "w1_20_39": 9421,
    "w1_40_59": 11554,
    "w1_60_69": 6226,
    "w1_70plus": 6132,
    "population": 58959,
    "atLeastOneDose": 36562,
    "fullyVaccinated": 35922
  },
  "3024": {
    "teryt": "3024",
    "w1_12_19": 4968,
    "w1_20_39": 17650,
    "w1_40_59": 20428,
    "w1_60_69": 9763,
    "w1_70plus": 9160,
    "population": 91745,
    "atLeastOneDose": 63797,
    "fullyVaccinated": 62583
  },
  "3025": {
    "teryt": "3025",
    "w1_12_19": 2703,
    "w1_20_39": 10389,
    "w1_40_59": 12263,
    "w1_60_69": 6210,
    "w1_70plus": 5694,
    "population": 59149,
    "atLeastOneDose": 38219,
    "fullyVaccinated": 37544
  },
  "3026": {
    "teryt": "3026",
    "w1_12_19": 2629,
    "w1_20_39": 9329,
    "w1_40_59": 11824,
    "w1_60_69": 6149,
    "w1_70plus": 5842,
    "population": 61492,
    "atLeastOneDose": 36595,
    "fullyVaccinated": 36023
  },
  "3027": {
    "teryt": "3027",
    "w1_12_19": 2550,
    "w1_20_39": 11711,
    "w1_40_59": 15511,
    "w1_60_69": 8256,
    "w1_70plus": 8145,
    "population": 83599,
    "atLeastOneDose": 46746,
    "fullyVaccinated": 45782
  },
  "3028": {
    "teryt": "3028",
    "w1_12_19": 3203,
    "w1_20_39": 11157,
    "w1_40_59": 13253,
    "w1_60_69": 7295,
    "w1_70plus": 6443,
    "population": 70096,
    "atLeastOneDose": 42241,
    "fullyVaccinated": 41046
  },
  "3029": {
    "teryt": "3029",
    "w1_12_19": 2478,
    "w1_20_39": 9383,
    "w1_40_59": 11219,
    "w1_60_69": 5321,
    "w1_70plus": 5451,
    "population": 57431,
    "atLeastOneDose": 34585,
    "fullyVaccinated": 33861
  },
  "3030": {
    "teryt": "3030",
    "w1_12_19": 3636,
    "w1_20_39": 13010,
    "w1_40_59": 15674,
    "w1_60_69": 7981,
    "w1_70plus": 7840,
    "population": 78037,
    "atLeastOneDose": 49323,
    "fullyVaccinated": 48453
  },
  "3031": {
    "teryt": "3031",
    "w1_12_19": 2766,
    "w1_20_39": 9289,
    "w1_40_59": 11591,
    "w1_60_69": 7129,
    "w1_70plus": 6442,
    "population": 69161,
    "atLeastOneDose": 37887,
    "fullyVaccinated": 37183
  },
  "3061": {
    "teryt": "3061",
    "w1_12_19": 3338,
    "w1_20_39": 12999,
    "w1_40_59": 18536,
    "w1_60_69": 10248,
    "w1_70plus": 13511,
    "population": 99106,
    "atLeastOneDose": 59580,
    "fullyVaccinated": 58305
  },
  "3062": {
    "teryt": "3062",
    "w1_12_19": 2593,
    "w1_20_39": 10048,
    "w1_40_59": 14226,
    "w1_60_69": 8379,
    "w1_70plus": 10639,
    "population": 72539,
    "atLeastOneDose": 46688,
    "fullyVaccinated": 45699
  },
  "3063": {
    "teryt": "3063",
    "w1_12_19": 2667,
    "w1_20_39": 9303,
    "w1_40_59": 12394,
    "w1_60_69": 6803,
    "w1_70plus": 7997,
    "population": 62854,
    "atLeastOneDose": 40032,
    "fullyVaccinated": 39292
  },
  "3064": {
    "teryt": "3064",
    "w1_12_19": 26421,
    "w1_20_39": 124735,
    "w1_40_59": 114957,
    "w1_60_69": 55612,
    "w1_70plus": 76058,
    "population": 532048,
    "atLeastOneDose": 412145,
    "fullyVaccinated": 403019
  },
  "3201": {
    "teryt": "3201",
    "w1_12_19": 1520,
    "w1_20_39": 5876,
    "w1_40_59": 7932,
    "w1_60_69": 4787,
    "w1_70plus": 4604,
    "population": 47304,
    "atLeastOneDose": 25038,
    "fullyVaccinated": 24385
  },
  "3202": {
    "teryt": "3202",
    "w1_12_19": 2054,
    "w1_20_39": 6936,
    "w1_40_59": 8894,
    "w1_60_69": 5524,
    "w1_70plus": 5269,
    "population": 47970,
    "atLeastOneDose": 29272,
    "fullyVaccinated": 28785
  },
  "3203": {
    "teryt": "3203",
    "w1_12_19": 2036,
    "w1_20_39": 7378,
    "w1_40_59": 9532,
    "w1_60_69": 6312,
    "w1_70plus": 6011,
    "population": 56482,
    "atLeastOneDose": 31761,
    "fullyVaccinated": 31059
  },
  "3204": {
    "teryt": "3204",
    "w1_12_19": 3352,
    "w1_20_39": 12283,
    "w1_40_59": 16001,
    "w1_60_69": 8798,
    "w1_70plus": 8063,
    "population": 82310,
    "atLeastOneDose": 49496,
    "fullyVaccinated": 48231
  },
  "3205": {
    "teryt": "3205",
    "w1_12_19": 2420,
    "w1_20_39": 8714,
    "w1_40_59": 11175,
    "w1_60_69": 6864,
    "w1_70plus": 6023,
    "population": 59844,
    "atLeastOneDose": 35803,
    "fullyVaccinated": 34866
  },
  "3206": {
    "teryt": "3206",
    "w1_12_19": 3123,
    "w1_20_39": 12165,
    "w1_40_59": 15432,
    "w1_60_69": 9275,
    "w1_70plus": 8128,
    "population": 81289,
    "atLeastOneDose": 48873,
    "fullyVaccinated": 47804
  },
  "3207": {
    "teryt": "3207",
    "w1_12_19": 1747,
    "w1_20_39": 6486,
    "w1_40_59": 8421,
    "w1_60_69": 5840,
    "w1_70plus": 5341,
    "population": 46692,
    "atLeastOneDose": 28311,
    "fullyVaccinated": 27558
  },
  "3208": {
    "teryt": "3208",
    "w1_12_19": 2936,
    "w1_20_39": 11613,
    "w1_40_59": 15935,
    "w1_60_69": 9438,
    "w1_70plus": 9773,
    "population": 79300,
    "atLeastOneDose": 50471,
    "fullyVaccinated": 49284
  },
  "3209": {
    "teryt": "3209",
    "w1_12_19": 2357,
    "w1_20_39": 8845,
    "w1_40_59": 12251,
    "w1_60_69": 7338,
    "w1_70plus": 5753,
    "population": 66505,
    "atLeastOneDose": 37129,
    "fullyVaccinated": 36272
  },
  "3210": {
    "teryt": "3210",
    "w1_12_19": 1909,
    "w1_20_39": 8597,
    "w1_40_59": 11501,
    "w1_60_69": 6895,
    "w1_70plus": 6588,
    "population": 65373,
    "atLeastOneDose": 35891,
    "fullyVaccinated": 34948
  },
  "3211": {
    "teryt": "3211",
    "w1_12_19": 3940,
    "w1_20_39": 12885,
    "w1_40_59": 18361,
    "w1_60_69": 8282,
    "w1_70plus": 6555,
    "population": 81584,
    "atLeastOneDose": 51448,
    "fullyVaccinated": 50203
  },
  "3212": {
    "teryt": "3212",
    "w1_12_19": 1273,
    "w1_20_39": 5088,
    "w1_40_59": 6847,
    "w1_60_69": 4244,
    "w1_70plus": 4169,
    "population": 39202,
    "atLeastOneDose": 21933,
    "fullyVaccinated": 21400
  },
  "3213": {
    "teryt": "3213",
    "w1_12_19": 2120,
    "w1_20_39": 7668,
    "w1_40_59": 9877,
    "w1_60_69": 6050,
    "w1_70plus": 5762,
    "population": 55777,
    "atLeastOneDose": 31945,
    "fullyVaccinated": 31174
  },
  "3214": {
    "teryt": "3214",
    "w1_12_19": 4457,
    "w1_20_39": 16781,
    "w1_40_59": 22196,
    "w1_60_69": 13380,
    "w1_70plus": 12996,
    "population": 120132,
    "atLeastOneDose": 71092,
    "fullyVaccinated": 69489
  },
  "3215": {
    "teryt": "3215",
    "w1_12_19": 2797,
    "w1_20_39": 9866,
    "w1_40_59": 13228,
    "w1_60_69": 8635,
    "w1_70plus": 8980,
    "population": 77258,
    "atLeastOneDose": 44232,
    "fullyVaccinated": 43256
  },
  "3216": {
    "teryt": "3216",
    "w1_12_19": 1739,
    "w1_20_39": 6490,
    "w1_40_59": 8113,
    "w1_60_69": 5516,
    "w1_70plus": 5024,
    "population": 46394,
    "atLeastOneDose": 27325,
    "fullyVaccinated": 26628
  },
  "3217": {
    "teryt": "3217",
    "w1_12_19": 2065,
    "w1_20_39": 7238,
    "w1_40_59": 9595,
    "w1_60_69": 5988,
    "w1_70plus": 5611,
    "population": 52707,
    "atLeastOneDose": 30983,
    "fullyVaccinated": 30264
  },
  "3218": {
    "teryt": "3218",
    "w1_12_19": 1350,
    "w1_20_39": 4810,
    "w1_40_59": 6240,
    "w1_60_69": 4150,
    "w1_70plus": 3868,
    "population": 36486,
    "atLeastOneDose": 20786,
    "fullyVaccinated": 20236
  },
  "3261": {
    "teryt": "3261",
    "w1_12_19": 3900,
    "w1_20_39": 14491,
    "w1_40_59": 19545,
    "w1_60_69": 11771,
    "w1_70plus": 15370,
    "population": 106235,
    "atLeastOneDose": 66306,
    "fullyVaccinated": 64849
  },
  "3262": {
    "teryt": "3262",
    "w1_12_19": 15994,
    "w1_20_39": 67590,
    "w1_40_59": 78631,
    "w1_60_69": 42886,
    "w1_70plus": 54079,
    "population": 398255,
    "atLeastOneDose": 265346,
    "fullyVaccinated": 259089
  },
  "3263": {
    "teryt": "3263",
    "w1_12_19": 1302,
    "w1_20_39": 5909,
    "w1_40_59": 8175,
    "w1_60_69": 4773,
    "w1_70plus": 5756,
    "population": 40948,
    "atLeastOneDose": 26215,
    "fullyVaccinated": 25522
  }
}
