{
  "02": {
    "teryt": "02",
    "w1_12_19": 86806,
    "w1_20_39": 415210,
    "w1_40_59": 492859,
    "w1_60_69": 304536,
    "w1_70plus": 299256,
    "population": 2891321,
    "atLeastOneDose": 1598685,
    "fullyVaccinated": 1559399
  },
  "04": {
    "teryt": "04",
    "w1_12_19": 72719,
    "w1_20_39": 276271,
    "w1_40_59": 366641,
    "w1_60_69": 214933,
    "w1_70plus": 203902,
    "population": 2061942,
    "atLeastOneDose": 1134468,
    "fullyVaccinated": 1109607
  },
  "06": {
    "teryt": "06",
    "w1_12_19": 49279,
    "w1_20_39": 224985,
    "w1_40_59": 308135,
    "w1_60_69": 193125,
    "w1_70plus": 194730,
    "population": 2095258,
    "atLeastOneDose": 970258,
    "fullyVaccinated": 938206
  },
  "08": {
    "teryt": "08",
    "w1_12_19": 32365,
    "w1_20_39": 134141,
    "w1_40_59": 178326,
    "w1_60_69": 107740,
    "w1_70plus": 96223,
    "population": 1007145,
    "atLeastOneDose": 548797,
    "fullyVaccinated": 534208
  },
  "10": {
    "teryt": "10",
    "w1_12_19": 69865,
    "w1_20_39": 311903,
    "w1_40_59": 422601,
    "w1_60_69": 259762,
    "w1_70plus": 268476,
    "population": 2437970,
    "atLeastOneDose": 1332616,
    "fullyVaccinated": 1299016
  },
  "12": {
    "teryt": "12",
    "w1_12_19": 98484,
    "w1_20_39": 498031,
    "w1_40_59": 563292,
    "w1_60_69": 294329,
    "w1_70plus": 300402,
    "population": 3410441,
    "atLeastOneDose": 1754542,
    "fullyVaccinated": 1717149
  },
  "14": {
    "teryt": "14",
    "w1_12_19": 198573,
    "w1_20_39": 876534,
    "w1_40_59": 1030869,
    "w1_60_69": 524031,
    "w1_70plus": 542422,
    "population": 5425028,
    "atLeastOneDose": 3172443,
    "fullyVaccinated": 3089594
  },
  "16": {
    "teryt": "16",
    "w1_12_19": 24647,
    "w1_20_39": 109305,
    "w1_40_59": 146949,
    "w1_60_69": 91921,
    "w1_70plus": 94906,
    "population": 976774,
    "atLeastOneDose": 467730,
    "fullyVaccinated": 456491
  },
  "18": {
    "teryt": "18",
    "w1_12_19": 37157,
    "w1_20_39": 201846,
    "w1_40_59": 272223,
    "w1_60_69": 164798,
    "w1_70plus": 162222,
    "population": 2121229,
    "atLeastOneDose": 838250,
    "fullyVaccinated": 816427
  },
  "20": {
    "teryt": "20",
    "w1_12_19": 24325,
    "w1_20_39": 121415,
    "w1_40_59": 163661,
    "w1_60_69": 101305,
    "w1_70plus": 102707,
    "population": 1173286,
    "atLeastOneDose": 513417,
    "fullyVaccinated": 497444
  },
  "22": {
    "teryt": "22",
    "w1_12_19": 86413,
    "w1_20_39": 360134,
    "w1_40_59": 414090,
    "w1_60_69": 225380,
    "w1_70plus": 222231,
    "population": 2346671,
    "atLeastOneDose": 1308253,
    "fullyVaccinated": 1275128
  },
  "24": {
    "teryt": "24",
    "w1_12_19": 136635,
    "w1_20_39": 582499,
    "w1_40_59": 789966,
    "w1_60_69": 465956,
    "w1_70plus": 464063,
    "population": 4492330,
    "atLeastOneDose": 2439127,
    "fullyVaccinated": 2386082
  },
  "26": {
    "teryt": "26",
    "w1_12_19": 31271,
    "w1_20_39": 141280,
    "w1_40_59": 198714,
    "w1_60_69": 127092,
    "w1_70plus": 126458,
    "population": 1224626,
    "atLeastOneDose": 624816,
    "fullyVaccinated": 609222
  },
  "28": {
    "teryt": "28",
    "w1_12_19": 44592,
    "w1_20_39": 171080,
    "w1_40_59": 232156,
    "w1_60_69": 145286,
    "w1_70plus": 126270,
    "population": 1416495,
    "atLeastOneDose": 719388,
    "fullyVaccinated": 700084
  },
  "30": {
    "teryt": "30",
    "w1_12_19": 125919,
    "w1_20_39": 535883,
    "w1_40_59": 649730,
    "w1_60_69": 347146,
    "w1_70plus": 329793,
    "population": 3496450,
    "atLeastOneDose": 1988481,
    "fullyVaccinated": 1941239
  },
  "32": {
    "teryt": "32",
    "w1_12_19": 52952,
    "w1_20_39": 220781,
    "w1_40_59": 293610,
    "w1_60_69": 184459,
    "w1_70plus": 171141,
    "population": 1688047,
    "atLeastOneDose": 922947,
    "fullyVaccinated": 898466
  }
}
